{
  "top-house x1013": {
    "codename": "X1013",
    "marketingName": "X1013",
    "manufacturer": "Top House",
    "brand": "Top House",
    "platform": "android",
    "type": "tablet",
    "pointingMethod": "touchscreen",
    "resolutionWidth": 1280,
    "resolutionHeight": 800,
    "dualOrientation": true
  },
  "top-house coto t117": {
    "codename": "Coto T117",
    "marketingName": "Coto T117",
    "manufacturer": "Top House",
    "brand": "Top House",
    "platform": "android",
    "type": "tablet",
    "pointingMethod": "touchscreen",
    "resolutionWidth": 800,
    "resolutionHeight": 480,
    "dualOrientation": true
  }
}
