{
  "general alcatel device": {
    "codename": "general Alcatel Device",
    "marketingName": "general Alcatel Device",
    "manufacturer": "Alcatel",
    "brand": "Alcatel",
    "platform": null,
    "type": "smartphone",
    "pointingMethod": "touchscreen",
    "resolutionWidth": null,
    "resolutionHeight": null,
    "dualOrientation": true
  },
  "alcatel 975n": {
    "codename": "975N",
    "marketingName": "Smart III",
    "manufacturer": "Alcatel",
    "brand": "Vodafone",
    "platform": "android",
    "type": "smartphone",
    "pointingMethod": "touchscreen",
    "resolutionWidth": 480,
    "resolutionHeight": 800,
    "dualOrientation": true
  },
  "alcatel fierce": {
    "codename": "Fierce",
    "marketingName": "One Touch Fierce",
    "manufacturer": "Alcatel",
    "brand": "Alcatel",
    "platform": "android",
    "type": "smartphone",
    "pointingMethod": "touchscreen",
    "resolutionWidth": 540,
    "resolutionHeight": 960,
    "dualOrientation": true
  },
  "alcatel fierce xl": {
    "codename": "Fierce XL",
    "marketingName": "Fierce XL",
    "manufacturer": "Alcatel",
    "brand": "Alcatel",
    "platform": null,
    "type": "smartphone",
    "pointingMethod": "touchscreen",
    "resolutionWidth": 720,
    "resolutionHeight": 1280,
    "dualOrientation": true
  },
  "alcatel m812c": {
    "codename": "M812C",
    "marketingName": "M812C",
    "manufacturer": "Alcatel",
    "brand": "Alcatel",
    "platform": "android",
    "type": "smartphone",
    "pointingMethod": "touchscreen",
    "resolutionWidth": 720,
    "resolutionHeight": 1280,
    "dualOrientation": true
  },
  "alcatel one touch 890d": {
    "codename": "OT-890D",
    "marketingName": "One Touch 890D",
    "manufacturer": "Alcatel",
    "brand": "Alcatel",
    "platform": "android",
    "type": "smartphone",
    "pointingMethod": "touchscreen",
    "resolutionWidth": 240,
    "resolutionHeight": 320,
    "dualOrientation": true
  },
  "alcatel ot-4007x": {
    "codename": "OT-4007X",
    "marketingName": "One Touch Pixi",
    "manufacturer": "Alcatel",
    "brand": "Alcatel",
    "platform": "android",
    "type": "smartphone",
    "pointingMethod": "touchscreen",
    "resolutionWidth": 320,
    "resolutionHeight": 480,
    "dualOrientation": true
  },
  "alcatel ot-4010d": {
    "codename": "OT-4010D",
    "marketingName": "One Touch T'Pop",
    "manufacturer": "Alcatel",
    "brand": "Alcatel",
    "platform": "android",
    "type": "smartphone",
    "pointingMethod": "touchscreen",
    "resolutionWidth": 320,
    "resolutionHeight": 480,
    "dualOrientation": true
  },
  "alcatel ot-4012a": {
    "codename": "OT-4012A",
    "marketingName": "One Touch Fire",
    "manufacturer": "Alcatel",
    "brand": "Alcatel",
    "platform": "firefoxos",
    "type": "smartphone",
    "pointingMethod": "touchscreen",
    "resolutionWidth": 320,
    "resolutionHeight": 480,
    "dualOrientation": true
  },
  "alcatel ot-4012x": {
    "codename": "OT-4012X",
    "marketingName": "One Touch Fire",
    "manufacturer": "Alcatel",
    "brand": "Alcatel",
    "platform": "firefoxos",
    "type": "smartphone",
    "pointingMethod": "touchscreen",
    "resolutionWidth": 320,
    "resolutionHeight": 480,
    "dualOrientation": true
  },
  "alcatel ot-4013m": {
    "codename": "OT-4013M",
    "marketingName": "One Touch Pixi 3 (4)",
    "manufacturer": "Alcatel",
    "brand": "Alcatel",
    "platform": "android",
    "type": "smartphone",
    "pointingMethod": "touchscreen",
    "resolutionWidth": 480,
    "resolutionHeight": 800,
    "dualOrientation": true
  },
  "alcatel ot-4015d": {
    "codename": "OT-4015D",
    "marketingName": "One Touch POP C1",
    "manufacturer": "Alcatel",
    "brand": "Alcatel",
    "platform": "android",
    "type": "smartphone",
    "pointingMethod": "touchscreen",
    "resolutionWidth": 320,
    "resolutionHeight": 480,
    "dualOrientation": true
  },
  "alcatel ot-4015x": {
    "codename": "OT-4015X",
    "marketingName": "One Touch POP C1",
    "manufacturer": "Alcatel",
    "brand": "Alcatel",
    "platform": "android",
    "type": "smartphone",
    "pointingMethod": "touchscreen",
    "resolutionWidth": 320,
    "resolutionHeight": 480,
    "dualOrientation": true
  },
  "alcatel ot-4019a": {
    "codename": "OT-4019A",
    "marketingName": "One Touch Fire C",
    "manufacturer": "Alcatel",
    "brand": "Alcatel",
    "platform": "firefoxos",
    "type": "smartphone",
    "pointingMethod": "touchscreen",
    "resolutionWidth": 320,
    "resolutionHeight": 480,
    "dualOrientation": true
  },
  "alcatel ot-4024d": {
    "codename": "OT-4024D",
    "marketingName": "One Touch Pixi First",
    "manufacturer": "Alcatel",
    "brand": "Alcatel",
    "platform": "android",
    "type": "smartphone",
    "pointingMethod": "touchscreen",
    "resolutionWidth": 480,
    "resolutionHeight": 800,
    "dualOrientation": true
  },
  "alcatel ot-4024x": {
    "codename": "OT-4024X",
    "marketingName": "One Touch Pixi First",
    "manufacturer": "Alcatel",
    "brand": "Alcatel",
    "platform": "android",
    "type": "smartphone",
    "pointingMethod": "touchscreen",
    "resolutionWidth": 480,
    "resolutionHeight": 800,
    "dualOrientation": true
  },
  "alcatel ot-4027d": {
    "codename": "OT-4027D",
    "marketingName": "One Touch Pixi 3 4.5",
    "manufacturer": "Alcatel",
    "brand": "Alcatel",
    "platform": null,
    "type": "smartphone",
    "pointingMethod": "touchscreen",
    "resolutionWidth": 480,
    "resolutionHeight": 854,
    "dualOrientation": true
  },
  "alcatel ot-4030a": {
    "codename": "OT-4030A",
    "marketingName": "One Touch S-POP",
    "manufacturer": "Alcatel",
    "brand": "Alcatel",
    "platform": "android",
    "type": "smartphone",
    "pointingMethod": "touchscreen",
    "resolutionWidth": 320,
    "resolutionHeight": 480,
    "dualOrientation": true
  },
  "alcatel ot-4030d": {
    "codename": "OT-4030D",
    "marketingName": "One Touch S-POP",
    "manufacturer": "Alcatel",
    "brand": "Alcatel",
    "platform": "android",
    "type": "smartphone",
    "pointingMethod": "touchscreen",
    "resolutionWidth": 320,
    "resolutionHeight": 480,
    "dualOrientation": true
  },
  "alcatel ot-4030x": {
    "codename": "OT-4030X",
    "marketingName": "One Touch S-POP",
    "manufacturer": "Alcatel",
    "brand": "Alcatel",
    "platform": null,
    "type": "smartphone",
    "pointingMethod": "touchscreen",
    "resolutionWidth": 320,
    "resolutionHeight": 480,
    "dualOrientation": true
  },
  "alcatel ot-4030y": {
    "codename": "OT-4030Y",
    "marketingName": "One Touch S-POP",
    "manufacturer": "Alcatel",
    "brand": "Alcatel",
    "platform": null,
    "type": "smartphone",
    "pointingMethod": "touchscreen",
    "resolutionWidth": 320,
    "resolutionHeight": 480,
    "dualOrientation": true
  },
  "alcatel ot-4033d": {
    "codename": "OT-4033D",
    "marketingName": "One Touch Pop C3",
    "manufacturer": "Alcatel",
    "brand": "Alcatel",
    "platform": "android",
    "type": "smartphone",
    "pointingMethod": "touchscreen",
    "resolutionWidth": 480,
    "resolutionHeight": 800,
    "dualOrientation": true
  },
  "alcatel ot-4034d": {
    "codename": "OT-4034D",
    "marketingName": "One Touch Pixi 4",
    "manufacturer": "Alcatel",
    "brand": "Alcatel",
    "platform": "android",
    "type": "smartphone",
    "pointingMethod": "touchscreen",
    "resolutionWidth": 480,
    "resolutionHeight": 800,
    "dualOrientation": true
  },
  "alcatel ot-4037t": {
    "codename": "OT-4037T",
    "marketingName": "One Touch Evolve II",
    "manufacturer": "Alcatel",
    "brand": "Alcatel",
    "platform": "android",
    "type": "smartphone",
    "pointingMethod": "touchscreen",
    "resolutionWidth": 480,
    "resolutionHeight": 800,
    "dualOrientation": true
  },
  "alcatel ot-5010d": {
    "codename": "OT-5010D",
    "marketingName": "One Touch Pixi 4 (5)",
    "manufacturer": "Alcatel",
    "brand": "Alcatel",
    "platform": "android",
    "type": "smartphone",
    "pointingMethod": "touchscreen",
    "resolutionWidth": 480,
    "resolutionHeight": 854,
    "dualOrientation": true
  },
  "alcatel ot-5020d": {
    "codename": "OT-5020D",
    "marketingName": "One Touch MPop",
    "manufacturer": "Alcatel",
    "brand": "Alcatel",
    "platform": "android",
    "type": "smartphone",
    "pointingMethod": "touchscreen",
    "resolutionWidth": 480,
    "resolutionHeight": 800,
    "dualOrientation": true
  },
  "alcatel ot-5020e": {
    "codename": "OT-5020E",
    "marketingName": "One Touch MPop",
    "manufacturer": "Alcatel",
    "brand": "Alcatel",
    "platform": "android",
    "type": "smartphone",
    "pointingMethod": "touchscreen",
    "resolutionWidth": 480,
    "resolutionHeight": 800,
    "dualOrientation": true
  },
  "alcatel ot-5020w": {
    "codename": "OT-5020W",
    "marketingName": "One Touch MPop",
    "manufacturer": "Alcatel",
    "brand": "Alcatel",
    "platform": "android",
    "type": "smartphone",
    "pointingMethod": "touchscreen",
    "resolutionWidth": 480,
    "resolutionHeight": 800,
    "dualOrientation": true
  },
  "alcatel ot-5022d": {
    "codename": "OT-5022D",
    "marketingName": "One Touch Pop Star 3G",
    "manufacturer": "Alcatel",
    "brand": "Alcatel",
    "platform": null,
    "type": "smartphone",
    "pointingMethod": "touchscreen",
    "resolutionWidth": 720,
    "resolutionHeight": 1280,
    "dualOrientation": true
  },
  "alcatel ot-5022x": {
    "codename": "OT-5022X",
    "marketingName": "One Touch Pop Star 3G",
    "manufacturer": "Alcatel",
    "brand": "Alcatel",
    "platform": null,
    "type": "smartphone",
    "pointingMethod": "touchscreen",
    "resolutionWidth": 720,
    "resolutionHeight": 1280,
    "dualOrientation": true
  },
  "alcatel ot-5025d": {
    "codename": "OT-5025D",
    "marketingName": "One Touch Pop 3 (5.5)",
    "manufacturer": "Alcatel",
    "brand": "Alcatel",
    "platform": "android",
    "type": "smartphone",
    "pointingMethod": "touchscreen",
    "resolutionWidth": 720,
    "resolutionHeight": 1280,
    "dualOrientation": true
  },
  "alcatel ot-5035d": {
    "codename": "OT-5035D",
    "marketingName": "One Touch XPop",
    "manufacturer": "Alcatel",
    "brand": "Alcatel",
    "platform": "android",
    "type": "smartphone",
    "pointingMethod": "touchscreen",
    "resolutionWidth": 540,
    "resolutionHeight": 960,
    "dualOrientation": true
  },
  "alcatel ot-5035e": {
    "codename": "OT-5035E",
    "marketingName": "One Touch XPop",
    "manufacturer": "Alcatel",
    "brand": "Alcatel",
    "platform": "android",
    "type": "smartphone",
    "pointingMethod": "touchscreen",
    "resolutionWidth": 540,
    "resolutionHeight": 960,
    "dualOrientation": true
  },
  "alcatel ot-5035y": {
    "codename": "OT-5035Y",
    "marketingName": "One Touch XPop",
    "manufacturer": "Alcatel",
    "brand": "Alcatel",
    "platform": "android",
    "type": "smartphone",
    "pointingMethod": "touchscreen",
    "resolutionWidth": 540,
    "resolutionHeight": 960,
    "dualOrientation": true
  },
  "alcatel ot-5036d": {
    "codename": "OT-5036D",
    "marketingName": "One Touch Pop C5",
    "manufacturer": "Alcatel",
    "brand": "Alcatel",
    "platform": "android",
    "type": "smartphone",
    "pointingMethod": "touchscreen",
    "resolutionWidth": 480,
    "resolutionHeight": 854,
    "dualOrientation": true
  },
  "alcatel ot-5036x": {
    "codename": "OT-5036X",
    "marketingName": "One Touch Pop C5",
    "manufacturer": "Alcatel",
    "brand": "Alcatel",
    "platform": "android",
    "type": "smartphone",
    "pointingMethod": "touchscreen",
    "resolutionWidth": 480,
    "resolutionHeight": 854,
    "dualOrientation": true
  },
  "alcatel ot-5038x": {
    "codename": "OT-5038X",
    "marketingName": "One Touch Pop D5",
    "manufacturer": "Alcatel",
    "brand": "Alcatel",
    "platform": "android",
    "type": "smartphone",
    "pointingMethod": "touchscreen",
    "resolutionWidth": 480,
    "resolutionHeight": 854,
    "dualOrientation": true
  },
  "alcatel ot-5042a": {
    "codename": "OT-5042A",
    "marketingName": "One Touch Pop 2 (4.5)",
    "manufacturer": "Alcatel",
    "brand": "Alcatel",
    "platform": "android",
    "type": "smartphone",
    "pointingMethod": "touchscreen",
    "resolutionWidth": 480,
    "resolutionHeight": 854,
    "dualOrientation": true
  },
  "alcatel ot-5042d": {
    "codename": "OT-5042D",
    "marketingName": "One Touch Pop 2 (4.5)",
    "manufacturer": "Alcatel",
    "brand": "Alcatel",
    "platform": "android",
    "type": "smartphone",
    "pointingMethod": "touchscreen",
    "resolutionWidth": 540,
    "resolutionHeight": 960,
    "dualOrientation": true
  },
  "alcatel ot-5045d": {
    "codename": "OT-5045D",
    "marketingName": "One Touch Pixi 4 (5)",
    "manufacturer": "Alcatel",
    "brand": "Alcatel",
    "platform": "android",
    "type": "smartphone",
    "pointingMethod": "touchscreen",
    "resolutionWidth": 480,
    "resolutionHeight": 854,
    "dualOrientation": true
  },
  "alcatel ot-5070d": {
    "codename": "OT-5070D",
    "marketingName": "One Touch Pop Star 4G",
    "manufacturer": "Alcatel",
    "brand": "Alcatel",
    "platform": null,
    "type": "smartphone",
    "pointingMethod": "touchscreen",
    "resolutionWidth": 720,
    "resolutionHeight": 1280,
    "dualOrientation": true
  },
  "alcatel ot-5070x": {
    "codename": "OT-5070X",
    "marketingName": "One Touch Pop Star 4G",
    "manufacturer": "Alcatel",
    "brand": "Alcatel",
    "platform": null,
    "type": "smartphone",
    "pointingMethod": "touchscreen",
    "resolutionWidth": 720,
    "resolutionHeight": 1280,
    "dualOrientation": true
  },
  "alcatel ot-6010d": {
    "codename": "OT-6010D",
    "marketingName": "One Touch Star",
    "manufacturer": "Alcatel",
    "brand": "Alcatel",
    "platform": "android",
    "type": "smartphone",
    "pointingMethod": "touchscreen",
    "resolutionWidth": 480,
    "resolutionHeight": 800,
    "dualOrientation": true
  },
  "alcatel ot-6010x": {
    "codename": "OT-6010X",
    "marketingName": "One Touch Star",
    "manufacturer": "Alcatel",
    "brand": "Alcatel",
    "platform": "android",
    "type": "smartphone",
    "pointingMethod": "touchscreen",
    "resolutionWidth": 480,
    "resolutionHeight": 800,
    "dualOrientation": true
  },
  "alcatel ot-6012a": {
    "codename": "OT-6012A",
    "marketingName": "One Touch Idol Mini",
    "manufacturer": "Alcatel",
    "brand": "Alcatel",
    "platform": "android",
    "type": "smartphone",
    "pointingMethod": "touchscreen",
    "resolutionWidth": 480,
    "resolutionHeight": 854,
    "dualOrientation": true
  },
  "alcatel ot-6012d": {
    "codename": "OT-6012D",
    "marketingName": "One Touch Idol Mini",
    "manufacturer": "Alcatel",
    "brand": "Alcatel",
    "platform": "android",
    "type": "smartphone",
    "pointingMethod": "touchscreen",
    "resolutionWidth": 480,
    "resolutionHeight": 854,
    "dualOrientation": true
  },
  "alcatel ot-6012e": {
    "codename": "OT-6012E",
    "marketingName": "One Touch Idol Mini",
    "manufacturer": "Alcatel",
    "brand": "Alcatel",
    "platform": "android",
    "type": "smartphone",
    "pointingMethod": "touchscreen",
    "resolutionWidth": 480,
    "resolutionHeight": 854,
    "dualOrientation": true
  },
  "alcatel ot-6012w": {
    "codename": "OT-6012W",
    "marketingName": "One Touch Idol Mini",
    "manufacturer": "Alcatel",
    "brand": "Alcatel",
    "platform": "android",
    "type": "smartphone",
    "pointingMethod": "touchscreen",
    "resolutionWidth": 480,
    "resolutionHeight": 854,
    "dualOrientation": true
  },
  "alcatel ot-6015x": {
    "codename": "OT-6015X",
    "marketingName": "One Touch Fire E",
    "manufacturer": "Alcatel",
    "brand": "Alcatel",
    "platform": "firefoxos",
    "type": "smartphone",
    "pointingMethod": "touchscreen",
    "resolutionWidth": 540,
    "resolutionHeight": 960,
    "dualOrientation": true
  },
  "alcatel ot-6016d": {
    "codename": "OT-6016D",
    "marketingName": "One Touch Idol 2 mini",
    "manufacturer": "Alcatel",
    "brand": "Alcatel",
    "platform": null,
    "type": "smartphone",
    "pointingMethod": "touchscreen",
    "resolutionWidth": 540,
    "resolutionHeight": 960,
    "dualOrientation": true
  },
  "alcatel ot-6016x": {
    "codename": "OT-6016X",
    "marketingName": "One Touch Idol 2 mini",
    "manufacturer": "Alcatel",
    "brand": "Alcatel",
    "platform": null,
    "type": "smartphone",
    "pointingMethod": "touchscreen",
    "resolutionWidth": 540,
    "resolutionHeight": 960,
    "dualOrientation": true
  },
  "alcatel ot-6030d": {
    "codename": "OT-6030D",
    "marketingName": "One Touch Idol",
    "manufacturer": "Alcatel",
    "brand": "Alcatel",
    "platform": "android",
    "type": "smartphone",
    "pointingMethod": "touchscreen",
    "resolutionWidth": 540,
    "resolutionHeight": 960,
    "dualOrientation": true
  },
  "alcatel ot-6030x": {
    "codename": "OT-6030X",
    "marketingName": "One Touch Idol",
    "manufacturer": "Alcatel",
    "brand": "Alcatel",
    "platform": "android",
    "type": "smartphone",
    "pointingMethod": "touchscreen",
    "resolutionWidth": 540,
    "resolutionHeight": 960,
    "dualOrientation": true
  },
  "alcatel ot-6032": {
    "codename": "OT-6032",
    "marketingName": "OneTouch Idol Alpha",
    "manufacturer": "Alcatel",
    "brand": "Alcatel",
    "platform": "android",
    "type": "smartphone",
    "pointingMethod": "touchscreen",
    "resolutionWidth": 720,
    "resolutionHeight": 1280,
    "dualOrientation": true
  },
  "alcatel ot-6033x": {
    "codename": "OT-6033X",
    "marketingName": "One Touch Idol Ultra",
    "manufacturer": "Alcatel",
    "brand": "Alcatel",
    "platform": "android",
    "type": "smartphone",
    "pointingMethod": "touchscreen",
    "resolutionWidth": 720,
    "resolutionHeight": 1280,
    "dualOrientation": true
  },
  "alcatel ot-6034m": {
    "codename": "OT-6034M",
    "marketingName": "One Touch Idol S",
    "manufacturer": "Alcatel",
    "brand": "Alcatel",
    "platform": "android",
    "type": "smartphone",
    "pointingMethod": "touchscreen",
    "resolutionWidth": 720,
    "resolutionHeight": 1280,
    "dualOrientation": true
  },
  "alcatel ot-6034r": {
    "codename": "OT-6034R",
    "marketingName": "One Touch Idol S",
    "manufacturer": "Alcatel",
    "brand": "Alcatel",
    "platform": "android",
    "type": "smartphone",
    "pointingMethod": "touchscreen",
    "resolutionWidth": 720,
    "resolutionHeight": 1280,
    "dualOrientation": true
  },
  "alcatel ot-6034y": {
    "codename": "OT-6034Y",
    "marketingName": "One Touch Idol S",
    "manufacturer": "Alcatel",
    "brand": "Alcatel",
    "platform": "android",
    "type": "smartphone",
    "pointingMethod": "touchscreen",
    "resolutionWidth": 720,
    "resolutionHeight": 1280,
    "dualOrientation": true
  },
  "alcatel ot-6035r": {
    "codename": "OT-6035R",
    "marketingName": "One Touch Idol S",
    "manufacturer": "Alcatel",
    "brand": "Alcatel",
    "platform": "android",
    "type": "smartphone",
    "pointingMethod": "touchscreen",
    "resolutionWidth": 720,
    "resolutionHeight": 1280,
    "dualOrientation": true
  },
  "alcatel ot-6036y": {
    "codename": "OT-6036Y",
    "marketingName": "One Touch Idol 2 Mini S",
    "manufacturer": "Alcatel",
    "brand": "Alcatel",
    "platform": "android",
    "type": "smartphone",
    "pointingMethod": "touchscreen",
    "resolutionWidth": 540,
    "resolutionHeight": 960,
    "dualOrientation": true
  },
  "alcatel ot-6037y": {
    "codename": "OT-6037Y",
    "marketingName": "One Touch Idol 2",
    "manufacturer": "Alcatel",
    "brand": "Alcatel",
    "platform": "android",
    "type": "smartphone",
    "pointingMethod": "touchscreen",
    "resolutionWidth": 540,
    "resolutionHeight": 960,
    "dualOrientation": true
  },
  "alcatel ot-6039y": {
    "codename": "OT-6039Y",
    "marketingName": "One Touch Idol 3 (4.7)",
    "manufacturer": "Alcatel",
    "brand": "Alcatel",
    "platform": null,
    "type": "smartphone",
    "pointingMethod": "touchscreen",
    "resolutionWidth": 720,
    "resolutionHeight": 1280,
    "dualOrientation": true
  },
  "alcatel ot-6040d": {
    "codename": "OT-6040D",
    "marketingName": "One Touch Idol X",
    "manufacturer": "Alcatel",
    "brand": "Alcatel",
    "platform": "android",
    "type": "smartphone",
    "pointingMethod": "touchscreen",
    "resolutionWidth": 1080,
    "resolutionHeight": 1920,
    "dualOrientation": true
  },
  "alcatel ot-6043d": {
    "codename": "OT-6043D",
    "marketingName": "One Touch Idol X+",
    "manufacturer": "Alcatel",
    "brand": "Alcatel",
    "platform": "android",
    "type": "smartphone",
    "pointingMethod": "touchscreen",
    "resolutionWidth": 1080,
    "resolutionHeight": 1920,
    "dualOrientation": true
  },
  "alcatel ot-6045y": {
    "codename": "OT-6045Y",
    "marketingName": "One Touch Idol 3 (5.5)",
    "manufacturer": "Alcatel",
    "brand": "Alcatel",
    "platform": null,
    "type": "smartphone",
    "pointingMethod": "touchscreen",
    "resolutionWidth": 1080,
    "resolutionHeight": 1920,
    "dualOrientation": true
  },
  "alcatel ot-6050a": {
    "codename": "OT-6050A",
    "marketingName": "One Touch Idol 2S",
    "manufacturer": "Alcatel",
    "brand": "Alcatel",
    "platform": "android",
    "type": "smartphone",
    "pointingMethod": "touchscreen",
    "resolutionWidth": 720,
    "resolutionHeight": 1280,
    "dualOrientation": true
  },
  "alcatel ot-6070k": {
    "codename": "OT-6070K",
    "marketingName": "One Touch Idol 4S",
    "manufacturer": "Alcatel",
    "brand": "Alcatel",
    "platform": "android",
    "type": "smartphone",
    "pointingMethod": "touchscreen",
    "resolutionWidth": 1440,
    "resolutionHeight": 2560,
    "dualOrientation": true
  },
  "alcatel ot-6070o": {
    "codename": "OT-6070O",
    "marketingName": "One Touch Idol 4S",
    "manufacturer": "Alcatel",
    "brand": "Alcatel",
    "platform": "android",
    "type": "smartphone",
    "pointingMethod": "touchscreen",
    "resolutionWidth": 1440,
    "resolutionHeight": 2560,
    "dualOrientation": true
  },
  "alcatel ot-6070y": {
    "codename": "OT-6070Y",
    "marketingName": "One Touch Idol 4S",
    "manufacturer": "Alcatel",
    "brand": "Alcatel",
    "platform": "android",
    "type": "smartphone",
    "pointingMethod": "touchscreen",
    "resolutionWidth": 1440,
    "resolutionHeight": 2560,
    "dualOrientation": true
  },
  "alcatel ot-7025d": {
    "codename": "OT-7025D",
    "marketingName": "One Touch Snap",
    "manufacturer": "Alcatel",
    "brand": "Alcatel",
    "platform": "android",
    "type": "smartphone",
    "pointingMethod": "touchscreen",
    "resolutionWidth": 540,
    "resolutionHeight": 960,
    "dualOrientation": true
  },
  "alcatel ot-7040a": {
    "codename": "OT-7040A",
    "marketingName": "One Touch Pop C7",
    "manufacturer": "Alcatel",
    "brand": "Alcatel",
    "platform": "android",
    "type": "smartphone",
    "pointingMethod": "touchscreen",
    "resolutionWidth": 480,
    "resolutionHeight": 854,
    "dualOrientation": true
  },
  "alcatel ot-7040d": {
    "codename": "OT-7040D",
    "marketingName": "One Touch Pop C7 Dual",
    "manufacturer": "Alcatel",
    "brand": "Alcatel",
    "platform": "android",
    "type": "smartphone",
    "pointingMethod": "touchscreen",
    "resolutionWidth": 480,
    "resolutionHeight": 854,
    "dualOrientation": true
  },
  "alcatel ot-7040e": {
    "codename": "OT-7040E",
    "marketingName": "One Touch Pop C7 Dual",
    "manufacturer": "Alcatel",
    "brand": "Alcatel",
    "platform": "android",
    "type": "smartphone",
    "pointingMethod": "touchscreen",
    "resolutionWidth": 480,
    "resolutionHeight": 854,
    "dualOrientation": true
  },
  "alcatel ot-7040f": {
    "codename": "OT-7040F",
    "marketingName": "One Touch Pop C7",
    "manufacturer": "Alcatel",
    "brand": "Alcatel",
    "platform": "android",
    "type": "smartphone",
    "pointingMethod": "touchscreen",
    "resolutionWidth": 480,
    "resolutionHeight": 854,
    "dualOrientation": true
  },
  "alcatel ot-7040n": {
    "codename": "OT-7040N",
    "marketingName": "One Touch Fierce 2",
    "manufacturer": "Alcatel",
    "brand": "Alcatel",
    "platform": "android",
    "type": "smartphone",
    "pointingMethod": "touchscreen",
    "resolutionWidth": 540,
    "resolutionHeight": 960,
    "dualOrientation": true
  },
  "alcatel ot-7041d": {
    "codename": "OT-7041D",
    "marketingName": "One Touch Pop C7 Dual",
    "manufacturer": "Alcatel",
    "brand": "Alcatel",
    "platform": "android",
    "type": "smartphone",
    "pointingMethod": "touchscreen",
    "resolutionWidth": 480,
    "resolutionHeight": 854,
    "dualOrientation": true
  },
  "alcatel ot-7041x": {
    "codename": "OT-7041X",
    "marketingName": "One Touch Pop C7",
    "manufacturer": "Alcatel",
    "brand": "Alcatel",
    "platform": "android",
    "type": "smartphone",
    "pointingMethod": "touchscreen",
    "resolutionWidth": 480,
    "resolutionHeight": 854,
    "dualOrientation": true
  },
  "alcatel ot-7047d": {
    "codename": "OT-7047D",
    "marketingName": "One Touch Pop C9",
    "manufacturer": "Alcatel",
    "brand": "Alcatel",
    "platform": "android",
    "type": "smartphone",
    "pointingMethod": "touchscreen",
    "resolutionWidth": 540,
    "resolutionHeight": 960,
    "dualOrientation": true
  },
  "alcatel ot-7049d": {
    "codename": "OT-7049D",
    "marketingName": "One Touch Flash 2",
    "manufacturer": "Alcatel",
    "brand": "Alcatel",
    "platform": "android",
    "type": "smartphone",
    "pointingMethod": "touchscreen",
    "resolutionWidth": 720,
    "resolutionHeight": 1280,
    "dualOrientation": true
  },
  "alcatel ot-7070x": {
    "codename": "OT-7070X",
    "marketingName": "One Touch Pop 4 (6)",
    "manufacturer": "Alcatel",
    "brand": "Alcatel",
    "platform": "android",
    "type": "smartphone",
    "pointingMethod": "touchscreen",
    "resolutionWidth": 720,
    "resolutionHeight": 1280,
    "dualOrientation": true
  },
  "alcatel ot-8000d": {
    "codename": "OT-8000D",
    "marketingName": "One Touch Scribe Easy",
    "manufacturer": "Alcatel",
    "brand": "Alcatel",
    "platform": "android",
    "type": "smartphone",
    "pointingMethod": "touchscreen",
    "resolutionWidth": 480,
    "resolutionHeight": 800,
    "dualOrientation": true
  },
  "alcatel ot-8008d": {
    "codename": "OT-8008D",
    "marketingName": "One Touch Scribe HD",
    "manufacturer": "Alcatel",
    "brand": "Alcatel",
    "platform": "android",
    "type": "smartphone",
    "pointingMethod": "touchscreen",
    "resolutionWidth": 720,
    "resolutionHeight": 1280,
    "dualOrientation": true
  },
  "alcatel ot-8030y": {
    "codename": "OT-8030Y",
    "marketingName": "One Touch Hero 2",
    "manufacturer": "Alcatel",
    "brand": "Alcatel",
    "platform": "android",
    "type": "smartphone",
    "pointingMethod": "touchscreen",
    "resolutionWidth": 1080,
    "resolutionHeight": 1920,
    "dualOrientation": true
  },
  "alcatel ot-8050d": {
    "codename": "OT-8050D",
    "marketingName": "One Touch Pixi 4",
    "manufacturer": "Alcatel",
    "brand": "Alcatel",
    "platform": null,
    "type": "smartphone",
    "pointingMethod": "touchscreen",
    "resolutionWidth": 540,
    "resolutionHeight": 960,
    "dualOrientation": true
  },
  "alcatel ot-890": {
    "codename": "OT-890",
    "marketingName": "OT-890",
    "manufacturer": "Alcatel",
    "brand": "Alcatel",
    "platform": "android",
    "type": "smartphone",
    "pointingMethod": "touchscreen",
    "resolutionWidth": 240,
    "resolutionHeight": 320,
    "dualOrientation": true
  },
  "alcatel ot-903": {
    "codename": "OT-903",
    "marketingName": "One Touch 903",
    "manufacturer": "Alcatel",
    "brand": "Alcatel",
    "platform": "android",
    "type": "smartphone",
    "pointingMethod": "touchscreen",
    "resolutionWidth": 240,
    "resolutionHeight": 320,
    "dualOrientation": true
  },
  "alcatel ot-903d": {
    "codename": "OT-903D",
    "marketingName": "One Touch 903D",
    "manufacturer": "Alcatel",
    "brand": "Alcatel",
    "platform": "android",
    "type": "smartphone",
    "pointingMethod": "touchscreen",
    "resolutionWidth": 240,
    "resolutionHeight": 320,
    "dualOrientation": true
  },
  "alcatel ot-908": {
    "codename": "OT-908",
    "marketingName": "OT-908",
    "manufacturer": "Alcatel",
    "brand": "Alcatel",
    "platform": "android",
    "type": "smartphone",
    "pointingMethod": "touchscreen",
    "resolutionWidth": 240,
    "resolutionHeight": 320,
    "dualOrientation": true
  },
  "alcatel ot-918": {
    "codename": "OT-918",
    "marketingName": "OT-918",
    "manufacturer": "Alcatel",
    "brand": "Alcatel",
    "platform": "android",
    "type": "smartphone",
    "pointingMethod": "touchscreen",
    "resolutionWidth": 320,
    "resolutionHeight": 480,
    "dualOrientation": true
  },
  "alcatel ot-918d": {
    "codename": "OT-918D",
    "marketingName": "One Touch 918D",
    "manufacturer": "Alcatel",
    "brand": "Alcatel",
    "platform": "android",
    "type": "smartphone",
    "pointingMethod": "touchscreen",
    "resolutionWidth": 320,
    "resolutionHeight": 480,
    "dualOrientation": true
  },
  "alcatel ot-980": {
    "codename": "OT-980",
    "marketingName": "OT-980",
    "manufacturer": "Alcatel",
    "brand": "Alcatel",
    "platform": "android",
    "type": "smartphone",
    "pointingMethod": "touchscreen",
    "resolutionWidth": 240,
    "resolutionHeight": 320,
    "dualOrientation": true
  },
  "alcatel ot-985d": {
    "codename": "OT-985D",
    "marketingName": "One Touch 985D",
    "manufacturer": "Alcatel",
    "brand": "Alcatel",
    "platform": "android",
    "type": "smartphone",
    "pointingMethod": "touchscreen",
    "resolutionWidth": 320,
    "resolutionHeight": 480,
    "dualOrientation": true
  },
  "alcatel ot-990": {
    "codename": "OT-990",
    "marketingName": "One Touch 990",
    "manufacturer": "Alcatel",
    "brand": "Alcatel",
    "platform": "android",
    "type": "smartphone",
    "pointingMethod": "touchscreen",
    "resolutionWidth": 320,
    "resolutionHeight": 480,
    "dualOrientation": true
  },
  "alcatel ot-991": {
    "codename": "OT-991",
    "marketingName": "One Touch 991",
    "manufacturer": "Alcatel",
    "brand": "Alcatel",
    "platform": "android",
    "type": "smartphone",
    "pointingMethod": "touchscreen",
    "resolutionWidth": 320,
    "resolutionHeight": 480,
    "dualOrientation": true
  },
  "alcatel ot-991d": {
    "codename": "OT-991D",
    "marketingName": "One Touch 991 Dual",
    "manufacturer": "Alcatel",
    "brand": "Alcatel",
    "platform": "android",
    "type": "smartphone",
    "pointingMethod": "touchscreen",
    "resolutionWidth": 320,
    "resolutionHeight": 480,
    "dualOrientation": true
  },
  "alcatel ot-991t": {
    "codename": "OT-991T",
    "marketingName": "One Touch 991T Play",
    "manufacturer": "Alcatel",
    "brand": "Alcatel",
    "platform": "android",
    "type": "smartphone",
    "pointingMethod": "touchscreen",
    "resolutionWidth": 320,
    "resolutionHeight": 480,
    "dualOrientation": true
  },
  "alcatel ot-992d": {
    "codename": "OT-992D",
    "marketingName": "One Touch 992 Play",
    "manufacturer": "Alcatel",
    "brand": "Alcatel",
    "platform": "android",
    "type": "smartphone",
    "pointingMethod": "touchscreen",
    "resolutionWidth": 480,
    "resolutionHeight": 800,
    "dualOrientation": true
  },
  "alcatel ot-995": {
    "codename": "OT-995",
    "marketingName": "One Touch Ultra 995",
    "manufacturer": "Alcatel",
    "brand": "Alcatel",
    "platform": "android",
    "type": "smartphone",
    "pointingMethod": "touchscreen",
    "resolutionWidth": 480,
    "resolutionHeight": 800,
    "dualOrientation": true
  },
  "alcatel ot-997d": {
    "codename": "OT-997D",
    "marketingName": "One Touch 997D",
    "manufacturer": "Alcatel",
    "brand": "Alcatel",
    "platform": "android",
    "type": "smartphone",
    "pointingMethod": "touchscreen",
    "resolutionWidth": 480,
    "resolutionHeight": 800,
    "dualOrientation": true
  },
  "alcatel v860": {
    "codename": "v860",
    "marketingName": "Smart II 3G",
    "manufacturer": "Alcatel",
    "brand": "Alcatel",
    "platform": "android",
    "type": "smartphone",
    "pointingMethod": "touchscreen",
    "resolutionWidth": 320,
    "resolutionHeight": 480,
    "dualOrientation": true
  },
  "alcatel vf-795": {
    "codename": "VF-795",
    "marketingName": "Smart Speed 6",
    "manufacturer": "Alcatel",
    "brand": "Vodafone",
    "platform": null,
    "type": "smartphone",
    "pointingMethod": "touchscreen",
    "resolutionWidth": 480,
    "resolutionHeight": 854,
    "dualOrientation": true
  },
  "alcatel vf-895n": {
    "codename": "VF-895N",
    "marketingName": "Smart Prime 6",
    "manufacturer": "Alcatel",
    "brand": "Vodafone",
    "platform": "android",
    "type": "smartphone",
    "pointingMethod": "touchscreen",
    "resolutionWidth": 720,
    "resolutionHeight": 1280,
    "dualOrientation": true
  },
  "alcatel vodafone 785": {
    "codename": "Vodafone 785",
    "marketingName": "Smart 4 Mini",
    "manufacturer": "Alcatel",
    "brand": "Vodafone",
    "platform": "android",
    "type": "smartphone",
    "pointingMethod": "touchscreen",
    "resolutionWidth": 480,
    "resolutionHeight": 800,
    "dualOrientation": true
  },
  "alcatel vodafone 875": {
    "codename": "Vodafone 875",
    "marketingName": "875",
    "manufacturer": "Alcatel",
    "brand": "Vodafone",
    "platform": "android",
    "type": "smartphone",
    "pointingMethod": "touchscreen",
    "resolutionWidth": 320,
    "resolutionHeight": 480,
    "dualOrientation": true
  },
  "alcatel ot-5015d": {
    "codename": "OT-5015D",
    "marketingName": "One Touch Pop 3 (5)",
    "manufacturer": "Alcatel",
    "brand": "Alcatel",
    "platform": "android",
    "type": "smartphone",
    "pointingMethod": "touchscreen",
    "resolutionWidth": 480,
    "resolutionHeight": 854,
    "dualOrientation": true
  },
  "alcatel ot-8020d": {
    "codename": "OT-8020D",
    "marketingName": "One Touch Hero Dual SIM",
    "manufacturer": "Alcatel",
    "brand": "Alcatel",
    "platform": "android",
    "type": "smartphone",
    "pointingMethod": "touchscreen",
    "resolutionWidth": 1080,
    "resolutionHeight": 1920,
    "dualOrientation": true
  },
  "alcatel ot-4007d": {
    "codename": "OT-4007D",
    "marketingName": "One Touch Pixi",
    "manufacturer": "Alcatel",
    "brand": "Alcatel",
    "platform": "android",
    "type": "smartphone",
    "pointingMethod": "touchscreen",
    "resolutionWidth": 320,
    "resolutionHeight": 480,
    "dualOrientation": true
  },
  "alcatel ot-4010a": {
    "codename": "OT-4010A",
    "marketingName": "One Touch TPop",
    "manufacturer": "Alcatel",
    "brand": "Alcatel",
    "platform": "android",
    "type": "smartphone",
    "pointingMethod": "touchscreen",
    "resolutionWidth": 320,
    "resolutionHeight": 480,
    "dualOrientation": true
  },
  "alcatel ot-4033e": {
    "codename": "OT-4033E",
    "marketingName": "One Touch POP C3 Dual",
    "manufacturer": "Alcatel",
    "brand": "Alcatel",
    "platform": "android",
    "type": "smartphone",
    "pointingMethod": "touchscreen",
    "resolutionWidth": 480,
    "resolutionHeight": 800,
    "dualOrientation": true
  },
  "alcatel ot-5020a": {
    "codename": "OT-5020A",
    "marketingName": "OT-5020A",
    "manufacturer": "Alcatel",
    "brand": "Alcatel",
    "platform": "android",
    "type": "smartphone",
    "pointingMethod": "touchscreen",
    "resolutionWidth": 480,
    "resolutionHeight": 800,
    "dualOrientation": true
  },
  "alcatel ot-5035x": {
    "codename": "OT-5035X",
    "marketingName": "One Touch 5035X",
    "manufacturer": "Alcatel",
    "brand": "Alcatel",
    "platform": "android",
    "type": "smartphone",
    "pointingMethod": "touchscreen",
    "resolutionWidth": 540,
    "resolutionHeight": 960,
    "dualOrientation": true
  },
  "alcatel ot-918a": {
    "codename": "OT-918A",
    "marketingName": "Blaze Duo",
    "manufacturer": "Alcatel",
    "brand": "Alcatel",
    "platform": "android",
    "type": "smartphone",
    "pointingMethod": "touchscreen",
    "resolutionWidth": 320,
    "resolutionHeight": 480,
    "dualOrientation": true
  },
  "alcatel ot-918s": {
    "codename": "OT-918S",
    "marketingName": "Blaze Duo",
    "manufacturer": "Alcatel",
    "brand": "Alcatel",
    "platform": "android",
    "type": "smartphone",
    "pointingMethod": "touchscreen",
    "resolutionWidth": 320,
    "resolutionHeight": 480,
    "dualOrientation": true
  },
  "alcatel ot-960c": {
    "codename": "OT-960C",
    "marketingName": "OT-960C",
    "manufacturer": "Alcatel",
    "brand": "Alcatel",
    "platform": "android",
    "type": "smartphone",
    "pointingMethod": "touchscreen",
    "resolutionWidth": 480,
    "resolutionHeight": 800,
    "dualOrientation": true
  },
  "alcatel ot-985": {
    "codename": "OT-985",
    "marketingName": "One Touch 985",
    "manufacturer": "Alcatel",
    "brand": "Alcatel",
    "platform": "android",
    "type": "smartphone",
    "pointingMethod": "touchscreen",
    "resolutionWidth": 320,
    "resolutionHeight": 480,
    "dualOrientation": true
  },
  "alcatel ot-990c+": {
    "codename": "OT-990C+",
    "marketingName": "One Touch 990C+",
    "manufacturer": "Alcatel",
    "brand": "Alcatel",
    "platform": "android",
    "type": "smartphone",
    "pointingMethod": "touchscreen",
    "resolutionWidth": null,
    "resolutionHeight": null,
    "dualOrientation": true
  },
  "alcatel ot-993d": {
    "codename": "OT-993D",
    "marketingName": "One Touch 993D",
    "manufacturer": "Alcatel",
    "brand": "Alcatel",
    "platform": "android",
    "type": "smartphone",
    "pointingMethod": "touchscreen",
    "resolutionWidth": 480,
    "resolutionHeight": 800,
    "dualOrientation": true
  },
  "alcatel ot-6050y": {
    "codename": "OT-6050Y",
    "marketingName": "One Touch Idol 2S",
    "manufacturer": "Alcatel",
    "brand": "Alcatel",
    "platform": "android",
    "type": "smartphone",
    "pointingMethod": "touchscreen",
    "resolutionWidth": 720,
    "resolutionHeight": 1280,
    "dualOrientation": true
  },
  "alcatel ot-6050f": {
    "codename": "OT-6050F",
    "marketingName": "One Touch Idol 2S",
    "manufacturer": "Alcatel",
    "brand": "Alcatel",
    "platform": "android",
    "type": "smartphone",
    "pointingMethod": "touchscreen",
    "resolutionWidth": 720,
    "resolutionHeight": 1280,
    "dualOrientation": true
  },
  "alcatel ot-6039h": {
    "codename": "OT-6039H",
    "marketingName": "One Touch Idol 3 4.7",
    "manufacturer": "Alcatel",
    "brand": "Alcatel",
    "platform": "android",
    "type": "smartphone",
    "pointingMethod": "touchscreen",
    "resolutionWidth": 720,
    "resolutionHeight": 1280,
    "dualOrientation": true
  },
  "alcatel ot-6055k": {
    "codename": "OT-6055K",
    "marketingName": "One Touch Idol 4",
    "manufacturer": "Alcatel",
    "brand": "Alcatel",
    "platform": "android",
    "type": "smartphone",
    "pointingMethod": "touchscreen",
    "resolutionWidth": 1080,
    "resolutionHeight": 1920,
    "dualOrientation": true
  },
  "alcatel ot-5015x": {
    "codename": "OT-5015X",
    "marketingName": "One Touch Pixi 3 5.0 3G",
    "manufacturer": "Alcatel",
    "brand": "Alcatel",
    "platform": "android",
    "type": "smartphone",
    "pointingMethod": "touchscreen",
    "resolutionWidth": 480,
    "resolutionHeight": 854,
    "dualOrientation": true
  },
  "alcatel ot-5065x": {
    "codename": "OT-5065X",
    "marketingName": "One Touch Pixi 3 5.0 LTE",
    "manufacturer": "Alcatel",
    "brand": "Alcatel",
    "platform": "android",
    "type": "smartphone",
    "pointingMethod": "touchscreen",
    "resolutionWidth": 480,
    "resolutionHeight": 854,
    "dualOrientation": true
  },
  "alcatel ot-5051x": {
    "codename": "OT-5051X",
    "marketingName": "One Touch Pop 4 LTE",
    "manufacturer": "Alcatel",
    "brand": "Alcatel",
    "platform": "android",
    "type": "smartphone",
    "pointingMethod": "touchscreen",
    "resolutionWidth": 720,
    "resolutionHeight": 1280,
    "dualOrientation": true
  },
  "alcatel 5095b": {
    "codename": "5095B",
    "marketingName": "One Touch Pop 4S",
    "manufacturer": "Tcl",
    "brand": "Alcatel",
    "platform": "android",
    "type": "smartphone",
    "pointingMethod": "touchscreen",
    "resolutionWidth": 1080,
    "resolutionHeight": 1920,
    "dualOrientation": true
  },
  "alcatel 5095i": {
    "codename": "5095I",
    "marketingName": "One Touch Pop 4S",
    "manufacturer": "Tcl",
    "brand": "Alcatel",
    "platform": "android",
    "type": "smartphone",
    "pointingMethod": "touchscreen",
    "resolutionWidth": 1080,
    "resolutionHeight": 1920,
    "dualOrientation": true
  },
  "alcatel 5095k": {
    "codename": "5095K",
    "marketingName": "One Touch Pop 4S",
    "manufacturer": "Tcl",
    "brand": "Alcatel",
    "platform": "android",
    "type": "smartphone",
    "pointingMethod": "touchscreen",
    "resolutionWidth": 1080,
    "resolutionHeight": 1920,
    "dualOrientation": true
  },
  "alcatel 5095y": {
    "codename": "5095Y",
    "marketingName": "One Touch Pop 4S",
    "manufacturer": "Tcl",
    "brand": "Alcatel",
    "platform": "android",
    "type": "smartphone",
    "pointingMethod": "touchscreen",
    "resolutionWidth": 1080,
    "resolutionHeight": 1920,
    "dualOrientation": true
  },
  "alcatel 5080x": {
    "codename": "5080X",
    "marketingName": "One Touch Shine Lite LTE",
    "manufacturer": "Tcl",
    "brand": "Alcatel",
    "platform": "android",
    "type": "smartphone",
    "pointingMethod": "touchscreen",
    "resolutionWidth": 1080,
    "resolutionHeight": 1920,
    "dualOrientation": true
  },
  "alcatel 9008x": {
    "codename": "9008X",
    "marketingName": "One Touch A3 XL",
    "manufacturer": "Tcl",
    "brand": "Alcatel",
    "platform": "android",
    "type": "smartphone",
    "pointingMethod": "touchscreen",
    "resolutionWidth": 720,
    "resolutionHeight": 1280,
    "dualOrientation": true
  },
  "alcatel 4013d": {
    "codename": "4013D",
    "marketingName": "One Touch Pixi 3 (4)",
    "manufacturer": "Tcl",
    "brand": "Alcatel",
    "platform": "android",
    "type": "smartphone",
    "pointingMethod": "touchscreen",
    "resolutionWidth": 480,
    "resolutionHeight": 800,
    "dualOrientation": true
  }
}
