{
  "rules": {
    "/opd2202/i": "oppo opd2202",
    "/opd2102/i": "oppo opd2102",
    "/pkv110/i": "oppo pkv110",
    "/pks110/i": "oppo pks110",
    "/pkp110/i": "oppo pkp110",
    "/pkm110/i": "oppo pkm110",
    "/pkk110/i": "oppo pkk110",
    "/pkh120/i": "oppo pkh120",
    "/pkh110/i": "oppo pkh110",
    "/pkd130/i": "oppo pkd130",
    "/pkd110/i": "oppo pkd110",
    "/pkc130/i": "oppo pkc130",
    "/pkc110/i": "oppo pkc110",
    "/pkb110/i": "oppo pkb110",
    "/pka110/i": "oppo pka110",
    "/pjy110/i": "oppo pjy110",
    "/pjw110/i": "oppo pjw110",
    "/pju110/i": "oppo pju110",
    "/pjt110/i": "oppo pjt110",
    "/pjs110/i": "oppo pjs110",
    "/pjh110/i": "oppo pjh110",
    "/pjg110/i": "oppo pjg110",
    "/pjc110/i": "oppo pjc110",
    "/pjb110/i": "oppo pjb110",
    "/phy110/i": "oppo phy110",
    "/phw110/i": "oppo phw110",
    "/phu110/i": "oppo phu110",
    "/pht110/i": "oppo pht110",
    "/phs110/i": "oppo phs110",
    "/phn110/i": "oppo phn110",
    "/phm110/i": "oppo phm110",
    "/phf110/i": "oppo phf110",
    "/pha120/i": "oppo pha120",
    "/pgw110/i": "oppo pgw110",
    "/pgu110/i": "oppo pgu110",
    "/pgt110/i": "oppo pgt110",
    "/pggm10/i": "oppo pggm10",
    "/pgfm10/i": "oppo pgfm10",
    "/pgem110/i": "oppo pgem110",
    "/pgem10/i": "oppo pgem10",
    "/pgbm10/i": "oppo pgbm10",
    "/pgam10/i": "oppo pgam10",
    "/pfum10/i": "oppo pfum10",
    "/pftm20/i": "oppo pftm20",
    "/pftm10/i": "oppo pftm10",
    "/pfgm00/i": "oppo pfgm00",
    "/pffm20/i": "oppo pffm20",
    "/pffm10/i": "oppo pffm10",
    "/pfem10/i": "oppo pfem10",
    "/pfdm00/i": "oppo pfdm00",
    "/pfcm00/i": "oppo pfcm00",
    "/perm10/i": "oppo perm10",
    "/perm00/i": "oppo perm00",
    "/peqm00/i": "oppo peqm00",
    "/pemt20/i": "oppo pemt20",
    "/pemt00/i": "oppo pemt00",
    "/pemm20/i": "oppo pemm20",
    "/pemm00/i": "oppo pemm00",
    "/pegt10/i": "oppo pegt10",
    "/pegt00/i": "oppo pegt00",
    "/pegm10/i": "oppo pegm10",
    "/pegm00/i": "oppo pegm00",
    "/pefm00/i": "oppo pefm00",
    "/peem00/i": "oppo peem00",
    "/pdyt20/i": "oppo pdyt20",
    "/pdyt10/i": "oppo pdyt10",
    "/pdym20/i": "oppo pdym20",
    "/pdym10/i": "oppo pdym10",
    "/pdst00/i": "oppo pdst00",
    "/pdsm00/i": "oppo pdsm00",
    "/pdrt00/i": "oppo pdrt00",
    "/pdrm00/i": "oppo pdrm00",
    "/pdct00/i": "oppo pdct00",
    "/pdbm00/i": "oppo pdbm00",
    "/ n1t[ )]/i": "oppo n1t",
    "/ n1[ )]/i": "oppo n1",
    "/ f1s[ )]/i": "oppo f1s",
    "/ a7[ )]/i": "oppo a7",
    "/a001op/i": "oppo a001op",
    "/opg02/i": "oppo opg02",
    "/cph2699/i": "oppo cph2699",
    "/cph2697/i": "oppo cph2697",
    "/cph2695/i": "oppo cph2695",
    "/cph2693/i": "oppo cph2693",
    "/cph2689/i": "oppo cph2689",
    "/cph2687/i": "oppo cph2687",
    "/cph2683/i": "oppo cph2683",
    "/cph2681/i": "oppo cph2681",
    "/cph2671/i": "oppo cph2671",
    "/cph2669/i": "oppo cph2669",
    "/cph2667/i": "oppo cph2667",
    "/cph2665/i": "oppo cph2665",
    "/cph2659/i": "oppo cph2659",
    "/cph2651/i": "oppo cph2651",
    "/cph2643/i": "oppo cph2643",
    "/cph2641/i": "oppo cph2641",
    "/cph2639/i": "oppo cph2639",
    "/cph2637/i": "oppo cph2637",
    "/cph2631/i": "oppo cph2631",
    "/cph2629/i": "oppo cph2629",
    "/cph2625/i": "oppo cph2625",
    "/cph2617/i": "oppo cph2617",
    "/cph2607/i": "oppo cph2607",
    "/cph2603/i": "oppo cph2603",
    "/cph2599/i": "oppo cph2599",
    "/cph2591/i": "oppo cph2591",
    "/cph2579/i": "oppo cph2579",
    "/cph2577/i": "oppo cph2577",
    "/cph2565/i": "oppo cph2565",
    "/cph2557/i": "oppo cph2557",
    "/cph2553/i": "oppo cph2553",
    "/cph2531/i": "oppo cph2531",
    "/cph2529/i": "oppo cph2529",
    "/cph2527/i": "oppo cph2527",
    "/cph2525/i": "oppo cph2525",
    "/cph2523/i": "oppo cph2523",
    "/cph2521/i": "oppo cph2521",
    "/cph2519/i": "oppo cph2519",
    "/cph2505/i": "oppo cph2505",
    "/cph2499/i": "oppo cph2499",
    "/cph2495/i": "oppo cph2495",
    "/cph2483/i": "oppo cph2483",
    "/cph2481/i": "oppo cph2481",
    "/cph2477/i": "oppo cph2477",
    "/cph2473/i": "oppo cph2473",
    "/cph2471/i": "oppo cph2471",
    "/cph2461/i": "oppo cph2461",
    "/cph2457/i": "oppo cph2457",
    "/cph2455/i": "oppo cph2455",
    "/cph2439/i": "oppo cph2439",
    "/cph2437/i": "oppo cph2437",
    "/cph2421/i": "oppo cph2421",
    "/cph2407/i": "oppo cph2407",
    "/cph2387/i": "oppo cph2387",
    "/cph2385/i": "oppo cph2385",
    "/cph2375/i": "oppo cph2375",
    "/cph2373/i": "oppo cph2373",
    "/cph2371/i": "oppo cph2371",
    "/cph2365/i": "oppo cph2365",
    "/cph2363/i": "oppo cph2363",
    "/cph2359/i": "oppo cph2359",
    "/cph2357/i": "oppo cph2357",
    "/cph2353/i": "oppo cph2353",
    "/cph2351/i": "oppo cph2351",
    "/cph2349/i": "oppo cph2349",
    "/cph2343/i": "oppo cph2343",
    "/cph2341/i": "oppo cph2341",
    "/cph2339/i": "oppo cph2339",
    "/cph2337/i": "oppo cph2337",
    "/cph2333/i": "oppo cph2333",
    "/cph2325/i": "oppo cph2325",
    "/cph2321/i": "oppo cph2321",
    "/cph2309/i": "oppo cph2309",
    "/cph2307/i": "oppo cph2307",
    "/cph2305/i": "oppo cph2305",
    "/cph2303/i": "oppo cph2303",
    "/cph2293/i": "oppo cph2293",
    "/cph2285/i": "oppo cph2285",
    "/cph2275/i": "oppo cph2275",
    "/cph2273/i": "oppo cph2273",
    "/cph2271/i": "oppo cph2271",
    "/cph2269/i": "oppo cph2269",
    "/cph2263/i": "oppo cph2263",
    "/cph2251/i": "oppo cph2251",
    "/cph2249/i": "oppo cph2249",
    "/cph2247/i": "oppo cph2247",
    "/cph2241/i": "oppo cph2241",
    "/cph2239/i": "oppo cph2239",
    "/cph2237/i": "oppo cph2237",
    "/cph2235/i": "oppo cph2235",
    "/cph2223/i": "oppo cph2223",
    "/cph2219/i": "oppo cph2219",
    "/cph2217/i": "oppo cph2217",
    "/cph2213/i": "oppo cph2213",
    "/cph2211/i": "oppo cph2211",
    "/cph2209/i": "oppo cph2209",
    "/cph2207/i": "oppo cph2207",
    "/cph2205/i": "oppo cph2205",
    "/cph2203/i": "oppo cph2203",
    "/cph2201/i": "oppo cph2201",
    "/cph2199/i": "oppo cph2199",
    "/cph2197/i": "oppo cph2197",
    "/cph2195/i": "oppo cph2195",
    "/cph2185/i": "oppo cph2185",
    "/cph2179/i": "oppo cph2179",
    "/cph2173/i": "oppo cph2173",
    "/cph2161/i": "oppo cph2161",
    "/cph2159/i": "oppo cph2159",
    "/cph2145/i": "oppo cph2145",
    "/cph2139/i": "oppo cph2139",
    "/cph2137/i": "oppo cph2137",
    "/cph2135/i": "oppo cph2135",
    "/cph2131/i": "oppo cph2131",
    "/cph2127/i": "oppo cph2127",
    "/cph2125/i": "oppo cph2125",
    "/cph2123/i": "oppo cph2123",
    "/cph2121/i": "oppo cph2121",
    "/cph2119/i": "oppo cph2119",
    "/cph2113/i": "oppo cph2113",
    "/cph2109/i": "oppo cph2109",
    "/cph2099/i": "oppo cph2099",
    "/cph2095/i": "oppo cph2095",
    "/cph2091/i": "oppo cph2091",
    "/cph2089/i": "oppo cph2089",
    "/cph2083/i": "oppo cph2083",
    "/cph2081/i": "oppo cph2081",
    "/cph2077/i": "oppo cph2077",
    "/cph2073/i": "oppo cph2073",
    "/cph2071/i": "oppo cph2071",
    "/cph2069/i": "oppo cph2069",
    "/cph2067/i": "oppo cph2067",
    "/cph2065/i": "oppo cph2065",
    "/cph2061/i": "oppo cph2061",
    "/cph2059/i": "oppo cph2059",
    "/cph2048/i": "oppo cph2048",
    "/cph2043/i": "oppo cph2043",
    "/cph2037/i": "oppo cph2037",
    "/cph2036/i": "oppo cph2036",
    "/cph2035/i": "oppo cph2035",
    "/cph2031/i": "oppo cph2031",
    "/cph2029/i": "oppo cph2029",
    "/cph2025/i": "oppo cph2025",
    "/cph2023/i": "oppo cph2023",
    "/cph2021/i": "oppo cph2021",
    "/cph2015/i": "oppo cph2015",
    "/cph2013/i": "oppo cph2013",
    "/cph2009/i": "oppo cph2009",
    "/cph2005/i": "oppo cph2005",
    "/cph2001/i": "oppo cph2001",
    "/cph1989/i": "oppo cph1989",
    "/cph1987/i": "oppo cph1987",
    "/cph1983/i": "oppo cph1983",
    "/cph1979/i": "oppo cph1979",
    "/cph1976/i": "oppo cph1976",
    "/cph1969/i": "oppo cph1969",
    "/cph1959/i": "oppo cph1959",
    "/cph1955/i": "oppo cph1955",
    "/cph1951/i": "oppo cph1951",
    "/cph1945/i": "oppo cph1945",
    "/cph1943/i": "oppo cph1943",
    "/cph1941/i": "oppo cph1941",
    "/cph1939/i": "oppo cph1939",
    "/cph1938/i": "oppo cph1938",
    "/cph1937/i": "oppo cph1937",
    "/cph1935/i": "oppo cph1935",
    "/cph1933/i": "oppo cph1933",
    "/cph1931/i": "oppo cph1931",
    "/cph1925/i": "oppo cph1925",
    "/cph1923/i": "oppo cph1923",
    "/cph1921/i": "oppo cph1921",
    "/cph1920/i": "oppo cph1920",
    "/cph1919/i": "oppo cph1919",
    "/cph1917/i": "oppo cph1917",
    "/cph1915/i": "oppo cph1915",
    "/cph1913/i": "oppo cph1913",
    "/cph1912/i": "oppo cph1912",
    "/cph1911/i": "oppo cph1911",
    "/cph1910/i": "oppo cph1910",
    "/cph1909/i": "oppo cph1909",
    "/cph1907/i": "oppo cph1907",
    "/cph1905/i": "oppo cph1905",
    "/cph1903/i": "oppo cph1903",
    "/cph1901/i": "oppo cph1901",
    "/cph1893/i": "oppo cph1893",
    "/cph1881/i": "oppo cph1881",
    "/cph1879/i": "oppo cph1879",
    "/cph1877/i": "oppo cph1877",
    "/cph1875/i": "oppo cph1875",
    "/cph1871/i": "oppo cph1871",
    "/cph1853/i": "oppo cph1853",
    "/cph1851/i": "oppo cph1851",
    "/cph1837/i": "oppo cph1837",
    "/cph1835/i": "oppo cph1835",
    "/cph1833/i": "oppo cph1833",
    "/cph1831/i": "oppo cph1831",
    "/cph1827/i": "oppo cph1827",
    "/cph1825/i": "oppo cph1825",
    "/cph1823/i": "oppo cph1823",
    "/cph1821/i": "oppo cph1821",
    "/cph1819/i": "oppo cph1819",
    "/cph1809/i": "oppo cph1809",
    "/cph1805/i": "oppo cph1805",
    "/cph1803/i": "oppo cph1803",
    "/cph1801/i": "oppo cph1801",
    "/cph1729/i": "oppo cph1729",
    "/cph1727/i": "oppo cph1727",
    "/cph1725/i": "oppo cph1725",
    "/cph1723/i": "oppo cph1723",
    "/cph1721/i": "oppo cph1721",
    "/cph1719/i": "oppo cph1719",
    "/cph1717/i": "oppo cph1717",
    "/cph1715/i": "oppo cph1715",
    "/cph1707/i": "oppo cph1707",
    "/cph1701/i": "oppo cph1701",
    "/cph1613/i": "oppo cph1613",
    "/cph1609/i": "oppo cph1609",
    "/cph1605/i": "oppo cph1605",
    "/f19[ _]pro/i": "oppo f19 pro",
    "/r15[ _]pro/i": "oppo r15 pro",
    "/r9tm/i": "oppo r9tm",
    "/r9st/i": "oppo r9st",
    "/r9s plus/i": "oppo r9s plus",
    "/r9sk/i": "oppo r9sk",
    "/cph1607|r9s/i": "oppo cph1607",
    "/r9 plusm a/i": "oppo r9 plusm a",
    "/r9m/i": "oppo r9m",
    "/pdpt00/i": "oppo pdpt00",
    "/pdpm00/i": "oppo pdpm00",
    "/pdnt00/i": "oppo pdnt00",
    "/pdnm00/i": "oppo pdnm00",
    "/pdkt00/i": "oppo pdkt00",
    "/pdkm00/i": "oppo pdkm00",
    "/pdhm00/i": "oppo pdhm00",
    "/pdet10/i": "oppo pdet10",
    "/pdem30/i": "oppo pdem30",
    "/pdem10/i": "oppo pdem10",
    "/pdcm00/i": "oppo pdcm00",
    "/pdam10/i": "oppo pdam10",
    "/pdam00/i": "oppo pdam00",
    "/pcrt00/i": "oppo pcrt00",
    "/pcrm00/i": "oppo pcrm00",
    "/pcpm00/i": "oppo pcpm00",
    "/pcnm00/i": "oppo pcnm00",
    "/pckt00/i": "oppo pckt00",
    "/pckm80/i": "oppo pckm80",
    "/pckm70/i": "oppo pckm70",
    "/pckm00/i": "oppo pckm00",
    "/pcht30/i": "oppo pcht30",
    "/pcht10/i": "oppo pcht10",
    "/pchm30/i": "oppo pchm30",
    "/pchm10/i": "oppo pchm10",
    "/pchm00/i": "oppo pchm00",
    "/pcgm00/i": "oppo pcgm00",
    "/pcet00/i": "oppo pcet00",
    "/pcem00/i": "oppo pcem00",
    "/pcdt10/i": "oppo pcdt10",
    "/pcdm10/i": "oppo pcdm10",
    "/pcdt00/i": "oppo pcdt00",
    "/pcdm00/i": "oppo pcdm00",
    "/pcct00/i": "oppo pcct00",
    "/pccm00/i": "oppo pccm00",
    "/pcat10/i": "oppo pcat10",
    "/pcat00/i": "oppo pcat00",
    "/pcam10/i": "oppo pcam10",
    "/pcam00/i": "oppo pcam00",
    "/peum00/i": "oppo peum00",
    "/pesm10/i": "oppo pesm10",
    "/pepm00/i": "oppo pepm00",
    "/penm00/i": "oppo penm00",
    "/peht00/i": "oppo peht00",
    "/pehm00/i": "oppo pehm00",
    "/pedm00/i": "oppo pedm00",
    "/pect30/i": "oppo pect30",
    "/pecm30/i": "oppo pecm30",
    "/pecm20/i": "oppo pecm20",
    "/peat00/i": "oppo peat00",
    "/peam00/i": "oppo peam00",
    "/pbft00/i": "oppo pbft00",
    "/pbfm00/i": "oppo pbfm00",
    "/pbet00/i": "oppo pbet00",
    "/pbem00/i": "oppo pbem00",
    "/pbdt00/i": "oppo pbdt00",
    "/pbdm00/i": "oppo pbdm00",
    "/pbct10/i": "oppo pbct10",
    "/pbcm30/i": "oppo pbcm30",
    "/pbcm10/i": "oppo pbcm10",
    "/pbbt30/i": "oppo pbbt30",
    "/pbbt00/i": "oppo pbbt00",
    "/pbbm30/i": "oppo pbbm30",
    "/pbbm00/i": "oppo pbbm00",
    "/pbat00/i": "oppo pbat00",
    "/pbam00/i": "oppo pbam00",
    "/pahm00/i": "oppo pahm00",
    "/paft00/i": "oppo paft00",
    "/pafm00/i": "oppo pafm00",
    "/padt00/i": "oppo padt00",
    "/padm00/i": "oppo padm00",
    "/pact00/i": "oppo pact00",
    "/pacm00/i": "oppo pacm00",
    "/paat00/i": "oppo paat00",
    "/paam00/i": "oppo paam00",
    "/blp705/i": "oppo blp705",
    "/x9077/i": "oppo x9077",
    "/x9076/i": "oppo x9076",
    "/x9070/i": "oppo x9070",
    "/x9017/i": "oppo x9017",
    "/x9015/i": "oppo x9015",
    "/x9009/i": "oppo x9009",
    "/x9007/i": "oppo x9007",
    "/x9006/i": "oppo x9006",
    "/x9000/i": "oppo x9000",
    "/x909t/i": "oppo x909t",
    "/x909/i": "oppo x909",
    "/x907/i": "oppo x907",
    "/x905/i": "oppo x905",
    "/x903/i": "oppo x903",
    "/n5209/i": "oppo n5209",
    "/n5207/i": "oppo n5207",
    "/n5206/i": "oppo n5206",
    "/n5117/i": "oppo n5117",
    "/n5116/i": "oppo n5116",
    "/n5111/i": "oppo n5111",
    "/a1603/i": "oppo a1603",
    "/a1601/i": "oppo a1601",
    "/a83t/i": "oppo a83t",
    "/a83/i": "oppo a83",
    "/a79/i": "oppo a79",
    "/a77t/i": "oppo a77t",
    "/a77/i": "oppo a77",
    "/a73/i": "oppo a73",
    "/a59t/i": "oppo a59t",
    "/a59s/i": "oppo a59s",
    "/a59m/i": "oppo a59m",
    "/a57t/i": "oppo a57t",
    "/a57/i": "oppo a57",
    "/a53/i": "oppo a53",
    "/a51w/i": "oppo a51w",
    "/a51f/i": "oppo a51f",
    "/a37m/i": "oppo a37m",
    "/a37fw/i": "oppo a37fw",
    "/a37f/i": "oppo a37f",
    "/a33w/i": "oppo a33w",
    "/a33t/i": "oppo a33t",
    "/a33m/i": "oppo a33m",
    "/a33f/i": "oppo a33f",
    "/a33c/i": "oppo a33c",
    "/a33/i": "oppo a33",
    "/a31c/i": "oppo a31c",
    "/a11w/i": "oppo a11w",
    "/find ?7/i": "oppo find 7",
    "/find ?5/i": "oppo find 5",
    "/u7015/i": "oppo u7015",
    "/u7011/i": "oppo u7011",
    "/u707t/i": "oppo u707t",
    "/u705t/i": "oppo u705t",
    "/u701t/i": "oppo u701t",
    "/u701/i": "oppo u701",
    "/r8207/i": "oppo r8207",
    "/r8206/i": "oppo r8206",
    "/r8205/i": "oppo r8205",
    "/r8200/i": "oppo r8200",
    "/r8111/i": "oppo r8111",
    "/r8109/i": "oppo r8109",
    "/r8107/i": "oppo r8107",
    "/r8106/i": "oppo r8106",
    "/r8007/i": "oppo r8007",
    "/r8006/i": "oppo r8006",
    "/r8000/i": "oppo r8000",
    "/r7007/i": "oppo r7007",
    "/r7005/i": "oppo r7005",
    "/r6007/i": "oppo r6007",
    "/r6006/i": "oppo r6006",
    "/r2017/i": "oppo r2017",
    "/r2010/i": "oppo r2010",
    "/r2001/i": "oppo r2001",
    "/r833t/i": "oppo r833t",
    "/r831t/i": "oppo r831t",
    "/r831l/i": "oppo r831l",
    "/r831k/i": "oppo r831k",
    "/r831/i": "oppo r831",
    "/r830s/i": "oppo r830s",
    "/r830/i": "oppo r830",
    "/r829t/i": "oppo r829t",
    "/r829/i": "oppo r829",
    "/r827t/i": "oppo r827t",
    "/r827/i": "oppo r827",
    "/r823t/i": "oppo r823t",
    "/r821t/i": "oppo r821t",
    "/r821/i": "oppo r821",
    "/r819t/i": "oppo r819t",
    "/r819/i": "oppo r819",
    "/r817/i": "oppo r817",
    "/r815w/i": "oppo r815w",
    "/r815t/i": "oppo r815t",
    "/r815/i": "oppo r815",
    "/r813t/i": "oppo r813t",
    "/r811/i": "oppo r811",
    "/r807/i": "oppo r807",
    "/r805/i": "oppo r805",
    "/r803/i": "oppo r803",
    "/r7t/i": "oppo r7t",
    "/r7sm/i": "oppo r7sm",
    "/r7sf/i": "oppo r7sf",
    "/r7s/i": "oppo r7s",
    "/r7plusm/i": "oppo r7plusm",
    "/r7plusf/i": "oppo r7 plus",
    "/r7kf/i": "oppo r7 lite",
    "/r7g/i": "oppo r7g",
    "/r7f/i": "oppo r7f",
    "/r7/i": "oppo r7",
    "/f1f/i": "oppo f1f",
    "/r1011/i": "oppo r1011",
    "/r1001/i": "oppo r1001",
    "/r801/i": "oppo r801",
    "/r1s/i": "oppo r1s",
    "/r1l/i": "oppo r1l",
    "/r11/i": "oppo r11",
    "/ r1[ )]/i": "oppo r1",
    "/t703/i": "oppo t703",
    "/t29/i": "oppo t29",
    "/1201/i": "oppo 1201",
    "/1107/i": "oppo 1107",
    "/a617/i": "oppo a617",
    "/a203/i": "oppo a203"
  },
  "generic": "general oppo device"
}
