{
  "samsung gt-n8005": {
    "deviceName": "GT-N8005",
    "marketingName": "Galaxy Note 10.1",
    "manufacturer": "Samsung",
    "brand": "Samsung",
    "display": {
      "width": 1280,
      "height": 800,
      "touch": true,
      "size": null
    },
    "dualOrientation": true,
    "type": "fone-pad",
    "simCount": 1,
    "market": {
      "regions": [],
      "countries": [],
      "vendors": []
    },
    "connections": [
      "LTE"
    ],
    "platform": "android",
    "variants": []
  },
  "samsung gt-n8020": {
    "deviceName": "GT-N8020",
    "marketingName": "Galaxy Note 10.1",
    "manufacturer": "Samsung",
    "brand": "Samsung",
    "display": {
      "width": 1280,
      "height": 800,
      "touch": true,
      "size": null
    },
    "dualOrientation": true,
    "type": "fone-pad",
    "simCount": 1,
    "market": {
      "regions": [],
      "countries": [],
      "vendors": []
    },
    "connections": [
      "LTE"
    ],
    "platform": "android",
    "variants": []
  },
  "samsung sm-p602": {
    "deviceName": "SM-P602",
    "marketingName": "Galaxy Note 10.1 (2014)",
    "manufacturer": "Samsung",
    "brand": "Samsung",
    "display": {
      "width": 2560,
      "height": 1600,
      "touch": true,
      "size": null
    },
    "dualOrientation": true,
    "type": "fone-pad",
    "simCount": 1,
    "market": {
      "regions": [],
      "countries": [],
      "vendors": []
    },
    "connections": [
      "GSM"
    ],
    "platform": null,
    "variants": []
  },
  "samsung sm-p607t": {
    "deviceName": "SM-P607T",
    "marketingName": "Galaxy Note 10.1 (2014)",
    "manufacturer": "Samsung",
    "brand": "Samsung",
    "display": {
      "width": 2560,
      "height": 1600,
      "touch": true,
      "size": null
    },
    "dualOrientation": true,
    "type": "fone-pad",
    "simCount": 1,
    "market": {
      "regions": [],
      "countries": [
        "USA"
      ],
      "vendors": [
        "T-Mobile"
      ]
    },
    "connections": [],
    "platform": "android",
    "variants": []
  },
  "samsung sm-p601": {
    "deviceName": "SM-P601",
    "marketingName": "Galaxy Note 10.1 2014 Edition 3G + Wifi",
    "manufacturer": "Samsung",
    "brand": "Samsung",
    "display": {
      "width": 2560,
      "height": 1600,
      "touch": true,
      "size": null
    },
    "dualOrientation": true,
    "type": "fone-pad",
    "simCount": 1,
    "market": {
      "regions": [],
      "countries": [],
      "vendors": []
    },
    "connections": [
      "GSM"
    ],
    "platform": "android",
    "variants": []
  },
  "samsung sm-p605": {
    "deviceName": "SM-P605",
    "marketingName": "Galaxy Note 10.1 2014 Edition WI-FI +",
    "manufacturer": "Samsung",
    "brand": "Samsung",
    "display": {
      "width": 2560,
      "height": 1600,
      "touch": true,
      "size": null
    },
    "dualOrientation": true,
    "type": "fone-pad",
    "simCount": 1,
    "market": {
      "regions": [],
      "countries": [],
      "vendors": []
    },
    "connections": [
      "LTE"
    ],
    "platform": "android",
    "variants": []
  },
  "samsung sm-n8000": {
    "deviceName": "SM-N8000",
    "marketingName": "Galaxy Note 10.1 3G",
    "manufacturer": "Samsung",
    "brand": "Samsung",
    "display": {
      "width": 1280,
      "height": 720,
      "touch": true,
      "size": null
    },
    "dualOrientation": true,
    "type": "fone-pad",
    "simCount": 1,
    "market": {
      "regions": [],
      "countries": [],
      "vendors": []
    },
    "connections": [
      "GSM"
    ],
    "platform": "android",
    "variants": []
  },
  "samsung gt-n8000": {
    "deviceName": "GT-N8000",
    "marketingName": "Galaxy Note 10.1 3G & WiFi",
    "manufacturer": "Samsung",
    "brand": "Samsung",
    "display": {
      "width": 1280,
      "height": 800,
      "touch": true,
      "size": null
    },
    "dualOrientation": true,
    "type": "fone-pad",
    "simCount": 1,
    "market": {
      "regions": [],
      "countries": [],
      "vendors": []
    },
    "connections": [
      "GSM"
    ],
    "platform": "android",
    "variants": []
  },
  "samsung gt-n8000d": {
    "deviceName": "GT-N8000D",
    "marketingName": "Galaxy Note 10.1 3G & WiFi",
    "manufacturer": "Samsung",
    "brand": "Samsung",
    "display": {
      "width": 1280,
      "height": 800,
      "touch": true,
      "size": null
    },
    "dualOrientation": true,
    "type": "fone-pad",
    "simCount": 1,
    "market": {
      "regions": [],
      "countries": [],
      "vendors": []
    },
    "connections": [
      "GSM"
    ],
    "platform": "android",
    "variants": []
  },
  "samsung gt-n5100": {
    "deviceName": "GT-N5100",
    "marketingName": "Galaxy Note 8.0",
    "manufacturer": "Samsung",
    "brand": "Samsung",
    "display": {
      "width": 1280,
      "height": 800,
      "touch": true,
      "size": null
    },
    "dualOrientation": true,
    "type": "fone-pad",
    "simCount": 1,
    "market": {
      "regions": [],
      "countries": [],
      "vendors": []
    },
    "connections": [],
    "platform": "android",
    "variants": []
  },
  "samsung gt-n5120": {
    "deviceName": "GT-N5120",
    "marketingName": "Galaxy Note 8.0",
    "manufacturer": "Samsung",
    "brand": "Samsung",
    "display": {
      "width": 1280,
      "height": 800,
      "touch": true,
      "size": null
    },
    "dualOrientation": true,
    "type": "fone-pad",
    "simCount": 1,
    "market": {
      "regions": [],
      "countries": [],
      "vendors": []
    },
    "connections": [
      "LTE"
    ],
    "platform": "android",
    "variants": []
  },
  "samsung sgh-i467": {
    "deviceName": "SGH-I467",
    "marketingName": "Galaxy Note 8.0",
    "manufacturer": "Samsung",
    "brand": "Samsung",
    "display": {
      "width": 1280,
      "height": 800,
      "touch": true,
      "size": null
    },
    "dualOrientation": true,
    "type": "fone-pad",
    "simCount": 1,
    "market": {
      "regions": [],
      "countries": [
        "USA"
      ],
      "vendors": [
        "AT&T"
      ]
    },
    "connections": [
      "LTE"
    ],
    "platform": "android",
    "variants": []
  },
  "samsung sm-p905": {
    "deviceName": "SM-P905",
    "marketingName": "Galaxy Note Pro 12.2",
    "manufacturer": "Samsung",
    "brand": "Samsung",
    "display": {
      "width": 2560,
      "height": 1600,
      "touch": true,
      "size": null
    },
    "dualOrientation": true,
    "type": "fone-pad",
    "simCount": 1,
    "market": {
      "regions": [],
      "countries": [],
      "vendors": []
    },
    "connections": [
      "LTE"
    ],
    "platform": "android",
    "variants": []
  },
  "samsung sm-p905m": {
    "deviceName": "SM-P905M",
    "marketingName": "Galaxy Note Pro 12.2",
    "manufacturer": "Samsung",
    "brand": "Samsung",
    "display": {
      "width": 2560,
      "height": 1600,
      "touch": true,
      "size": null
    },
    "dualOrientation": true,
    "type": "fone-pad",
    "simCount": 1,
    "market": {
      "regions": [],
      "countries": [],
      "vendors": []
    },
    "connections": [
      "LTE"
    ],
    "platform": "android",
    "variants": []
  },
  "samsung sm-p905v": {
    "deviceName": "SM-P905V",
    "marketingName": "Galaxy Note Pro 12.2",
    "manufacturer": "Samsung",
    "brand": "Samsung",
    "display": {
      "width": 2560,
      "height": 1600,
      "touch": true,
      "size": null
    },
    "dualOrientation": true,
    "type": "fone-pad",
    "simCount": 1,
    "market": {
      "regions": [],
      "countries": [],
      "vendors": []
    },
    "connections": [
      "LTE"
    ],
    "platform": "android",
    "variants": []
  },
  "samsung sm-p907a": {
    "deviceName": "SM-P907A",
    "marketingName": "Galaxy Note Pro 12.2",
    "manufacturer": "Samsung",
    "brand": "Samsung",
    "display": {
      "width": 2560,
      "height": 1600,
      "touch": true,
      "size": null
    },
    "dualOrientation": true,
    "type": "fone-pad",
    "simCount": 1,
    "market": {
      "regions": [],
      "countries": [
        "USA"
      ],
      "vendors": [
        "AT&T"
      ]
    },
    "connections": [
      "LTE"
    ],
    "platform": "android",
    "variants": []
  },
  "samsung sm-p901": {
    "deviceName": "SM-P901",
    "marketingName": "Galaxy Note Pro 12.2  + 3G",
    "manufacturer": "Samsung",
    "brand": "Samsung",
    "display": {
      "width": 2560,
      "height": 1600,
      "touch": true,
      "size": null
    },
    "dualOrientation": true,
    "type": "fone-pad",
    "simCount": 1,
    "market": {
      "regions": [],
      "countries": [],
      "vendors": []
    },
    "connections": [
      "Wi-Fi",
      "GSM"
    ],
    "platform": "android",
    "variants": []
  },
  "samsung gt-p7500": {
    "deviceName": "GT-P7500",
    "marketingName": "Galaxy Tab 10.1 3G",
    "manufacturer": "Samsung",
    "brand": "Samsung",
    "display": {
      "width": 1280,
      "height": 800,
      "touch": true,
      "size": null
    },
    "dualOrientation": true,
    "type": "fone-pad",
    "simCount": 1,
    "market": {
      "regions": [],
      "countries": [],
      "vendors": []
    },
    "connections": [
      "GSM"
    ],
    "platform": "android",
    "variants": []
  },
  "samsung gt-p7500m": {
    "deviceName": "GT-P7500M",
    "marketingName": "Galaxy Tab 10.1 3G",
    "manufacturer": "Samsung",
    "brand": "Samsung",
    "display": {
      "width": 1280,
      "height": 800,
      "touch": true,
      "size": null
    },
    "dualOrientation": true,
    "type": "fone-pad",
    "simCount": 1,
    "market": {
      "regions": [],
      "countries": [],
      "vendors": []
    },
    "connections": [
      "GSM"
    ],
    "platform": "android",
    "variants": []
  },
  "samsung shw-m380k": {
    "deviceName": "SHW-M380K",
    "marketingName": "Galaxy Tab 10.1 3G",
    "manufacturer": "Samsung",
    "brand": "Samsung",
    "display": {
      "width": 1280,
      "height": 800,
      "touch": true,
      "size": null
    },
    "dualOrientation": true,
    "type": "fone-pad",
    "simCount": 1,
    "market": {
      "regions": [],
      "countries": [],
      "vendors": []
    },
    "connections": [
      "GSM"
    ],
    "platform": "android",
    "variants": []
  },
  "samsung gt-p5100": {
    "deviceName": "GT-P5100",
    "marketingName": "Galaxy Tab 2 10.1",
    "manufacturer": "Samsung",
    "brand": "Samsung",
    "display": {
      "width": 1280,
      "height": 800,
      "touch": true,
      "size": null
    },
    "dualOrientation": true,
    "type": "fone-pad",
    "simCount": 1,
    "market": {
      "regions": [],
      "countries": [],
      "vendors": []
    },
    "connections": [],
    "platform": "android",
    "variants": []
  },
  "samsung sch-i915": {
    "deviceName": "SCH-I915",
    "marketingName": "Galaxy Tab 2 10.1",
    "manufacturer": "Samsung",
    "brand": "Samsung",
    "display": {
      "width": 1280,
      "height": 800,
      "touch": true,
      "size": null
    },
    "dualOrientation": true,
    "type": "fone-pad",
    "simCount": 1,
    "market": {
      "regions": [],
      "countries": [
        "USA"
      ],
      "vendors": [
        "Verizon"
      ]
    },
    "connections": [
      "CDMA"
    ],
    "platform": "android",
    "variants": []
  },
  "samsung sgh-i497": {
    "deviceName": "SGH-I497",
    "marketingName": "Galaxy Tab 2 10.1",
    "manufacturer": "Samsung",
    "brand": "Samsung",
    "display": {
      "width": 1280,
      "height": 800,
      "touch": true,
      "size": null
    },
    "dualOrientation": true,
    "type": "fone-pad",
    "simCount": 1,
    "market": {
      "regions": [],
      "countries": [
        "USA"
      ],
      "vendors": [
        "AT&T"
      ]
    },
    "connections": [
      "CDMA"
    ],
    "platform": "android",
    "variants": []
  },
  "samsung sgh-t779": {
    "deviceName": "SGH-T779",
    "marketingName": "Galaxy Tab 2 10.1",
    "manufacturer": "Samsung",
    "brand": "Samsung",
    "display": {
      "width": 1280,
      "height": 800,
      "touch": true,
      "size": null
    },
    "dualOrientation": true,
    "type": "fone-pad",
    "simCount": 1,
    "market": {
      "regions": [],
      "countries": [
        "USA"
      ],
      "vendors": [
        "T-Mobile"
      ]
    },
    "connections": [
      "CDMA"
    ],
    "platform": "android",
    "variants": []
  },
  "samsung sph-p500": {
    "deviceName": "SPH-P500",
    "marketingName": "Galaxy Tab 2 10.1",
    "manufacturer": "Samsung",
    "brand": "Samsung",
    "display": {
      "width": 1280,
      "height": 800,
      "touch": true,
      "size": null
    },
    "dualOrientation": true,
    "type": "fone-pad",
    "simCount": 1,
    "market": {
      "regions": [],
      "countries": [
        "USA"
      ],
      "vendors": [
        "Sprint"
      ]
    },
    "connections": [
      "CDMA"
    ],
    "platform": "android",
    "variants": []
  },
  "samsung gt-p3100": {
    "deviceName": "GT-P3100",
    "marketingName": "Galaxy Tab 2 7.0 3G",
    "manufacturer": "Samsung",
    "brand": "Samsung",
    "display": {
      "width": 1024,
      "height": 600,
      "touch": true,
      "size": null
    },
    "dualOrientation": true,
    "type": "fone-pad",
    "simCount": 1,
    "market": {
      "regions": [],
      "countries": [],
      "vendors": []
    },
    "connections": [
      "GSM"
    ],
    "platform": "android",
    "variants": []
  },
  "samsung gt-p3100b": {
    "deviceName": "GT-P3100B",
    "marketingName": "Galaxy Tab 2 7.0 3G",
    "manufacturer": "Samsung",
    "brand": "Samsung",
    "display": {
      "width": 1024,
      "height": 600,
      "touch": true,
      "size": null
    },
    "dualOrientation": true,
    "type": "fone-pad",
    "simCount": 1,
    "market": {
      "regions": [],
      "countries": [],
      "vendors": []
    },
    "connections": [
      "GSM"
    ],
    "platform": "android",
    "variants": []
  },
  "samsung gt-p5220": {
    "deviceName": "GT-P5220",
    "marketingName": "Galaxy Tab 3 10.1",
    "manufacturer": "Samsung",
    "brand": "Samsung",
    "display": {
      "width": 1280,
      "height": 800,
      "touch": true,
      "size": null
    },
    "dualOrientation": true,
    "type": "fone-pad",
    "simCount": 1,
    "market": {
      "regions": [],
      "countries": [],
      "vendors": []
    },
    "connections": [
      "LTE"
    ],
    "platform": "android",
    "variants": []
  },
  "samsung gt-p5200": {
    "deviceName": "GT-P5200",
    "marketingName": "Galaxy Tab 3 10.1 3G",
    "manufacturer": "Samsung",
    "brand": "Samsung",
    "display": {
      "width": 1280,
      "height": 800,
      "touch": true,
      "size": null
    },
    "dualOrientation": true,
    "type": "fone-pad",
    "simCount": 1,
    "market": {
      "regions": [],
      "countries": [],
      "vendors": []
    },
    "connections": [
      "GSM"
    ],
    "platform": "android",
    "variants": []
  },
  "samsung gt-p5210": {
    "deviceName": "GT-P5210",
    "marketingName": "Galaxy Tab 3 10.1 3G WiFi",
    "manufacturer": "Samsung",
    "brand": "Samsung",
    "display": {
      "width": 1280,
      "height": 800,
      "touch": true,
      "size": null
    },
    "dualOrientation": true,
    "type": "fone-pad",
    "simCount": 1,
    "market": {
      "regions": [],
      "countries": [],
      "vendors": []
    },
    "connections": [
      "GSM"
    ],
    "platform": "android",
    "variants": []
  },
  "samsung sm-t217a": {
    "deviceName": "SM-T217A",
    "marketingName": "Galaxy Tab 3 7.0",
    "manufacturer": "Samsung",
    "brand": "Samsung",
    "display": {
      "width": 1024,
      "height": 600,
      "touch": true,
      "size": null
    },
    "dualOrientation": true,
    "type": "fone-pad",
    "simCount": 1,
    "market": {
      "regions": [],
      "countries": [
        "USA"
      ],
      "vendors": [
        "AT&T"
      ]
    },
    "connections": [
      "LTE"
    ],
    "platform": "android",
    "variants": []
  },
  "samsung sm-t217s": {
    "deviceName": "SM-T217S",
    "marketingName": "Galaxy Tab 3 7.0",
    "manufacturer": "Samsung",
    "brand": "Samsung",
    "display": {
      "width": 1024,
      "height": 600,
      "touch": true,
      "size": null
    },
    "dualOrientation": true,
    "type": "fone-pad",
    "simCount": 1,
    "market": {
      "regions": [],
      "countries": [
        "USA"
      ],
      "vendors": [
        "Sprint"
      ]
    },
    "connections": [
      "LTE",
      "CDMA"
    ],
    "platform": "android",
    "variants": []
  },
  "samsung sm-t211": {
    "deviceName": "SM-T211",
    "marketingName": "Galaxy Tab 3 7.0 3G",
    "manufacturer": "Samsung",
    "brand": "Samsung",
    "display": {
      "width": 1024,
      "height": 600,
      "touch": true,
      "size": null
    },
    "dualOrientation": true,
    "type": "fone-pad",
    "simCount": 1,
    "market": {
      "regions": [],
      "countries": [],
      "vendors": []
    },
    "connections": [
      "GSM"
    ],
    "platform": "android",
    "variants": []
  },
  "samsung sm-t315": {
    "deviceName": "SM-T315",
    "marketingName": "Galaxy Tab 3 8.0",
    "manufacturer": "Samsung",
    "brand": "Samsung",
    "display": {
      "width": 1280,
      "height": 800,
      "touch": true,
      "size": null
    },
    "dualOrientation": true,
    "type": "fone-pad",
    "simCount": 1,
    "market": {
      "regions": [],
      "countries": [],
      "vendors": []
    },
    "connections": [
      "LTE"
    ],
    "platform": "android",
    "variants": []
  },
  "samsung sm-t335": {
    "deviceName": "SM-T335",
    "marketingName": "Galaxy Tab 3 8.0",
    "manufacturer": "Samsung",
    "brand": "Samsung",
    "display": {
      "width": 1280,
      "height": 800,
      "touch": true,
      "size": null
    },
    "dualOrientation": true,
    "type": "fone-pad",
    "simCount": 1,
    "market": {
      "regions": [],
      "countries": [],
      "vendors": []
    },
    "connections": [
      "LTE"
    ],
    "platform": "android",
    "variants": []
  },
  "samsung sm-t311": {
    "deviceName": "SM-T311",
    "marketingName": "Galaxy Tab 3 8.0 3G",
    "manufacturer": "Samsung",
    "brand": "Samsung",
    "display": {
      "width": 1280,
      "height": 800,
      "touch": true,
      "size": null
    },
    "dualOrientation": true,
    "type": "fone-pad",
    "simCount": 1,
    "market": {
      "regions": [],
      "countries": [],
      "vendors": []
    },
    "connections": [
      "GSM"
    ],
    "platform": "android",
    "variants": []
  },
  "samsung sm-t116": {
    "deviceName": "SM-T116",
    "marketingName": "Galaxy Tab 3 Lite (7.0)",
    "manufacturer": "Samsung",
    "brand": "Samsung",
    "display": {
      "width": 1024,
      "height": 600,
      "touch": true,
      "size": null
    },
    "dualOrientation": true,
    "type": "fone-pad",
    "simCount": 1,
    "market": {
      "regions": [],
      "countries": [],
      "vendors": []
    },
    "connections": [
      "GSM"
    ],
    "platform": "android",
    "variants": []
  },
  "samsung sm-t111": {
    "deviceName": "SM-T111",
    "marketingName": "Galaxy Tab 3 Lite 7.0 3G",
    "manufacturer": "Samsung",
    "brand": "Samsung",
    "display": {
      "width": 1024,
      "height": 600,
      "touch": true,
      "size": null
    },
    "dualOrientation": true,
    "type": "fone-pad",
    "simCount": 1,
    "market": {
      "regions": [],
      "countries": [],
      "vendors": []
    },
    "connections": [
      "GSM"
    ],
    "platform": "android",
    "variants": []
  },
  "samsung sm-t116bu": {
    "deviceName": "SM-T116BU",
    "marketingName": "Galaxy Tab 3 V",
    "manufacturer": "Samsung",
    "brand": "Samsung",
    "display": {
      "width": 1024,
      "height": 600,
      "touch": true,
      "size": null
    },
    "dualOrientation": true,
    "type": "fone-pad",
    "simCount": 1,
    "market": {
      "regions": [],
      "countries": [],
      "vendors": []
    },
    "connections": [],
    "platform": "android",
    "variants": []
  },
  "samsung sm-t116nu": {
    "deviceName": "SM-T116NU",
    "marketingName": "Galaxy Tab 3 V",
    "manufacturer": "Samsung",
    "brand": "Samsung",
    "display": {
      "width": 1024,
      "height": 600,
      "touch": true,
      "size": null
    },
    "dualOrientation": true,
    "type": "fone-pad",
    "simCount": 1,
    "market": {
      "regions": [],
      "countries": [],
      "vendors": []
    },
    "connections": [],
    "platform": "android",
    "variants": []
  },
  "samsung sm-t530nu": {
    "deviceName": "SM-T530NU",
    "marketingName": "Galaxy Tab 4 10.1",
    "manufacturer": "Samsung",
    "brand": "Samsung",
    "display": {
      "width": 1280,
      "height": 800,
      "touch": true,
      "size": null
    },
    "dualOrientation": true,
    "type": "fone-pad",
    "simCount": 1,
    "market": {
      "regions": [],
      "countries": [],
      "vendors": []
    },
    "connections": [],
    "platform": "android",
    "variants": []
  },
  "samsung sm-t535": {
    "deviceName": "SM-T535",
    "marketingName": "Galaxy Tab 4 10.1",
    "manufacturer": "Samsung",
    "brand": "Samsung",
    "display": {
      "width": 1280,
      "height": 800,
      "touch": true,
      "size": null
    },
    "dualOrientation": true,
    "type": "fone-pad",
    "simCount": 1,
    "market": {
      "regions": [],
      "countries": [],
      "vendors": []
    },
    "connections": [
      "LTE"
    ],
    "platform": "android",
    "variants": []
  },
  "samsung sm-t533": {
    "deviceName": "SM-T533",
    "marketingName": "Galaxy Tab 4 10.1 (2015)",
    "manufacturer": "Samsung",
    "brand": "Samsung",
    "display": {
      "width": 1280,
      "height": 800,
      "touch": true,
      "size": null
    },
    "dualOrientation": true,
    "type": "fone-pad",
    "simCount": 1,
    "market": {
      "regions": [],
      "countries": [],
      "vendors": []
    },
    "connections": [],
    "platform": "android",
    "variants": []
  },
  "samsung sm-t531": {
    "deviceName": "SM-T531",
    "marketingName": "Galaxy Tab 4 10.1 3G",
    "manufacturer": "Samsung",
    "brand": "Samsung",
    "display": {
      "width": 1280,
      "height": 800,
      "touch": true,
      "size": null
    },
    "dualOrientation": true,
    "type": "fone-pad",
    "simCount": 1,
    "market": {
      "regions": [],
      "countries": [],
      "vendors": []
    },
    "connections": [
      "GSM"
    ],
    "platform": "android",
    "variants": []
  },
  "samsung sm-t530": {
    "deviceName": "SM-T530",
    "marketingName": "Galaxy Tab 4 10.1 WiFi",
    "manufacturer": "Samsung",
    "brand": "Samsung",
    "display": {
      "width": 1280,
      "height": 800,
      "touch": true,
      "size": null
    },
    "dualOrientation": true,
    "type": "fone-pad",
    "simCount": 1,
    "market": {
      "regions": [],
      "countries": [],
      "vendors": []
    },
    "connections": [],
    "platform": "android",
    "variants": []
  },
  "samsung sm-t235": {
    "deviceName": "SM-T235",
    "marketingName": "Galaxy Tab 4 7.0 WiFi +",
    "manufacturer": "Samsung",
    "brand": "Samsung",
    "display": {
      "width": 1280,
      "height": 800,
      "touch": true,
      "size": null
    },
    "dualOrientation": true,
    "type": "fone-pad",
    "simCount": 1,
    "market": {
      "regions": [],
      "countries": [],
      "vendors": []
    },
    "connections": [
      "LTE"
    ],
    "platform": "android",
    "variants": []
  },
  "samsung sm-t337a": {
    "deviceName": "SM-T337A",
    "marketingName": "Galaxy Tab 4 8.0",
    "manufacturer": "Samsung",
    "brand": "Samsung",
    "display": {
      "width": 1280,
      "height": 800,
      "touch": true,
      "size": null
    },
    "dualOrientation": true,
    "type": "fone-pad",
    "simCount": 1,
    "market": {
      "regions": [],
      "countries": [
        "USA"
      ],
      "vendors": [
        "AT&T"
      ]
    },
    "connections": [],
    "platform": "android",
    "variants": []
  },
  "samsung sm-t331": {
    "deviceName": "SM-T331",
    "marketingName": "Galaxy Tab 4 8.0 3G",
    "manufacturer": "Samsung",
    "brand": "Samsung",
    "display": {
      "width": 1280,
      "height": 800,
      "touch": true,
      "size": null
    },
    "dualOrientation": true,
    "type": "fone-pad",
    "simCount": 1,
    "market": {
      "regions": [],
      "countries": [],
      "vendors": []
    },
    "connections": [
      "GSM"
    ],
    "platform": "android",
    "variants": []
  },
  "samsung gt-p1000n": {
    "deviceName": "GT-P1000N",
    "marketingName": "Galaxy Tab 7.0",
    "manufacturer": "Samsung",
    "brand": "Samsung",
    "display": {
      "width": 1024,
      "height": 600,
      "touch": true,
      "size": null
    },
    "dualOrientation": true,
    "type": "fone-pad",
    "simCount": 1,
    "market": {
      "regions": [],
      "countries": [
        "USA"
      ],
      "vendors": []
    },
    "connections": [
      "GSM"
    ],
    "platform": "android",
    "variants": []
  },
  "samsung sch-i800": {
    "deviceName": "SCH-I800",
    "marketingName": "Galaxy Tab 7.0",
    "manufacturer": "Samsung",
    "brand": "Samsung",
    "display": {
      "width": 1024,
      "height": 600,
      "touch": true,
      "size": null
    },
    "dualOrientation": true,
    "type": "fone-pad",
    "simCount": 1,
    "market": {
      "regions": [],
      "countries": [
        "USA"
      ],
      "vendors": [
        "Verizon"
      ]
    },
    "connections": [
      "CDMA"
    ],
    "platform": "android",
    "variants": []
  },
  "samsung sph-p100": {
    "deviceName": "SPH-P100",
    "marketingName": "Galaxy Tab 7.0",
    "manufacturer": "Samsung",
    "brand": "Samsung",
    "display": {
      "width": 1024,
      "height": 600,
      "touch": true,
      "size": null
    },
    "dualOrientation": true,
    "type": "fone-pad",
    "simCount": 1,
    "market": {
      "regions": [],
      "countries": [],
      "vendors": []
    },
    "connections": [],
    "platform": "android",
    "variants": []
  },
  "samsung sch-i815": {
    "deviceName": "SCH-I815",
    "marketingName": "Galaxy Tab 7.7  +",
    "manufacturer": "Samsung",
    "brand": "Samsung",
    "display": {
      "width": 1280,
      "height": 800,
      "touch": true,
      "size": null
    },
    "dualOrientation": true,
    "type": "fone-pad",
    "simCount": 1,
    "market": {
      "regions": [],
      "countries": [
        "USA"
      ],
      "vendors": [
        "Verizon"
      ]
    },
    "connections": [
      "LTE",
      "CDMA"
    ],
    "platform": "android",
    "variants": []
  },
  "samsung gt-p7320": {
    "deviceName": "GT-P7320",
    "marketingName": "Galaxy Tab 8.9",
    "manufacturer": "Samsung",
    "brand": "Samsung",
    "display": {
      "width": 1280,
      "height": 800,
      "touch": true,
      "size": null
    },
    "dualOrientation": true,
    "type": "fone-pad",
    "simCount": 1,
    "market": {
      "regions": [],
      "countries": [],
      "vendors": []
    },
    "connections": [
      "LTE"
    ],
    "platform": "android",
    "variants": []
  },
  "samsung sgh-i957": {
    "deviceName": "SGH-I957",
    "marketingName": "Galaxy Tab 8.9",
    "manufacturer": "Samsung",
    "brand": "Samsung",
    "display": {
      "width": 1280,
      "height": 800,
      "touch": true,
      "size": null
    },
    "dualOrientation": true,
    "type": "fone-pad",
    "simCount": 1,
    "market": {
      "regions": [],
      "countries": [],
      "vendors": []
    },
    "connections": [
      "LTE"
    ],
    "platform": "android",
    "variants": []
  },
  "samsung sgh-i957r": {
    "deviceName": "SGH-I957R",
    "marketingName": "Galaxy Tab 8.9",
    "manufacturer": "Samsung",
    "brand": "Samsung",
    "display": {
      "width": 1280,
      "height": 800,
      "touch": true,
      "size": null
    },
    "dualOrientation": true,
    "type": "fone-pad",
    "simCount": 1,
    "market": {
      "regions": [],
      "countries": [],
      "vendors": []
    },
    "connections": [
      "LTE"
    ],
    "platform": "android",
    "variants": []
  },
  "samsung shv-e140l": {
    "deviceName": "SHV-E140L",
    "marketingName": "Galaxy Tab 8.9",
    "manufacturer": "Samsung",
    "brand": "Samsung",
    "display": {
      "width": 1280,
      "height": 800,
      "touch": true,
      "size": null
    },
    "dualOrientation": true,
    "type": "fone-pad",
    "simCount": 1,
    "market": {
      "regions": [],
      "countries": [],
      "vendors": []
    },
    "connections": [],
    "platform": "android",
    "variants": []
  },
  "samsung shw-m305w": {
    "deviceName": "SHW-M305W",
    "marketingName": "Galaxy Tab 8.9",
    "manufacturer": "Samsung",
    "brand": "Samsung",
    "display": {
      "width": 1280,
      "height": 800,
      "touch": true,
      "size": null
    },
    "dualOrientation": true,
    "type": "fone-pad",
    "simCount": 1,
    "market": {
      "regions": [],
      "countries": [],
      "vendors": []
    },
    "connections": [],
    "platform": "android",
    "variants": []
  },
  "samsung sm-t595": {
    "deviceName": "SM-T595",
    "marketingName": "Galaxy Tab A (10.5)",
    "manufacturer": "Samsung",
    "brand": "Samsung",
    "display": {
      "width": 1920,
      "height": 1200,
      "touch": true,
      "size": null
    },
    "dualOrientation": true,
    "type": "fone-pad",
    "simCount": 1,
    "market": {
      "regions": [],
      "countries": [],
      "vendors": []
    },
    "connections": [
      "LTE"
    ],
    "platform": "android",
    "variants": []
  },
  "samsung sm-t585": {
    "deviceName": "SM-T585",
    "marketingName": "Galaxy Tab A (2016, 10.1)",
    "manufacturer": "Samsung",
    "brand": "Samsung",
    "display": {
      "width": 1920,
      "height": 1200,
      "touch": true,
      "size": null
    },
    "dualOrientation": true,
    "type": "fone-pad",
    "simCount": 1,
    "market": {
      "regions": [],
      "countries": [],
      "vendors": []
    },
    "connections": [
      "LTE"
    ],
    "platform": "android",
    "variants": []
  },
  "samsung sm-t585n0": {
    "deviceName": "SM-T585N0",
    "marketingName": "Galaxy Tab A (2016, 10.1)",
    "manufacturer": "Samsung",
    "brand": "Samsung",
    "display": {
      "width": 1920,
      "height": 1200,
      "touch": true,
      "size": null
    },
    "dualOrientation": true,
    "type": "fone-pad",
    "simCount": 1,
    "market": {
      "regions": [],
      "countries": [],
      "vendors": []
    },
    "connections": [
      "LTE"
    ],
    "platform": "android",
    "variants": []
  },
  "samsung sm-t285": {
    "deviceName": "SM-T285",
    "marketingName": "Galaxy Tab A (7.0, 2016)",
    "manufacturer": "Samsung",
    "brand": "Samsung",
    "display": {
      "width": 1280,
      "height": 800,
      "touch": true,
      "size": null
    },
    "dualOrientation": true,
    "type": "fone-pad",
    "simCount": 1,
    "market": {
      "regions": [],
      "countries": [],
      "vendors": []
    },
    "connections": [
      "Wi-Fi",
      "LTE"
    ],
    "platform": "android",
    "variants": []
  },
  "samsung sm-p585": {
    "deviceName": "SM-P585",
    "marketingName": "Galaxy Tab A 10.1 (2017)",
    "manufacturer": "Samsung",
    "brand": "Samsung",
    "display": {
      "width": 1920,
      "height": 1200,
      "touch": true,
      "size": null
    },
    "dualOrientation": true,
    "type": "fone-pad",
    "simCount": 1,
    "market": {
      "regions": [],
      "countries": [],
      "vendors": []
    },
    "connections": [],
    "platform": "android",
    "variants": []
  },
  "samsung sm-p355": {
    "deviceName": "SM-P355",
    "marketingName": "Galaxy Tab A 8.0",
    "manufacturer": "Samsung",
    "brand": "Samsung",
    "display": {
      "width": 2560,
      "height": 1600,
      "touch": true,
      "size": null
    },
    "dualOrientation": true,
    "type": "fone-pad",
    "simCount": 1,
    "market": {
      "regions": [],
      "countries": [],
      "vendors": []
    },
    "connections": [
      "LTE"
    ],
    "platform": "android",
    "variants": []
  },
  "samsung sm-t355y": {
    "deviceName": "SM-T355Y",
    "marketingName": "Galaxy Tab A 8.0",
    "manufacturer": "Samsung",
    "brand": "Samsung",
    "display": {
      "width": 1024,
      "height": 768,
      "touch": true,
      "size": null
    },
    "dualOrientation": true,
    "type": "fone-pad",
    "simCount": 1,
    "market": {
      "regions": [],
      "countries": [],
      "vendors": []
    },
    "connections": [
      "LTE"
    ],
    "platform": "android",
    "variants": []
  },
  "samsung sm-t385": {
    "deviceName": "SM-T385",
    "marketingName": "Galaxy Tab A 8.0 (2017)",
    "manufacturer": "Samsung",
    "brand": "Samsung",
    "display": {
      "width": 1280,
      "height": 800,
      "touch": true,
      "size": null
    },
    "dualOrientation": true,
    "type": "fone-pad",
    "simCount": 1,
    "market": {
      "regions": [],
      "countries": [],
      "vendors": []
    },
    "connections": [],
    "platform": "android",
    "variants": []
  },
  "samsung sm-t385l": {
    "deviceName": "SM-T385L",
    "marketingName": "Galaxy Tab A 8.0 (2017)",
    "manufacturer": "Samsung",
    "brand": "Samsung",
    "display": {
      "width": 1280,
      "height": 800,
      "touch": true,
      "size": null
    },
    "dualOrientation": true,
    "type": "fone-pad",
    "simCount": 1,
    "market": {
      "regions": [],
      "countries": [],
      "vendors": []
    },
    "connections": [],
    "platform": "android",
    "variants": []
  },
  "samsung sm-t355": {
    "deviceName": "SM-T355",
    "marketingName": "Galaxy Tab A 8.0 3G",
    "manufacturer": "Samsung",
    "brand": "Samsung",
    "display": {
      "width": 1024,
      "height": 768,
      "touch": true,
      "size": null
    },
    "dualOrientation": true,
    "type": "fone-pad",
    "simCount": 1,
    "market": {
      "regions": [],
      "countries": [],
      "vendors": []
    },
    "connections": [
      "GSM"
    ],
    "platform": "android",
    "variants": []
  },
  "samsung sm-t555": {
    "deviceName": "SM-T555",
    "marketingName": "Galaxy Tab A 9.7",
    "manufacturer": "Samsung",
    "brand": "Samsung",
    "display": {
      "width": 1024,
      "height": 768,
      "touch": true,
      "size": null
    },
    "dualOrientation": true,
    "type": "fone-pad",
    "simCount": 1,
    "market": {
      "regions": [],
      "countries": [],
      "vendors": []
    },
    "connections": [
      "LTE"
    ],
    "platform": "android",
    "variants": []
  },
  "samsung sm-p555": {
    "deviceName": "SM-P555",
    "marketingName": "Galaxy Tab A 9.7 WiFi+ with S Pen",
    "manufacturer": "Samsung",
    "brand": "Samsung",
    "display": {
      "width": 1024,
      "height": 768,
      "touch": true,
      "size": null
    },
    "dualOrientation": true,
    "type": "fone-pad",
    "simCount": 1,
    "market": {
      "regions": [],
      "countries": [],
      "vendors": []
    },
    "connections": [
      "LTE"
    ],
    "platform": "android",
    "variants": []
  },
  "samsung sm-t390": {
    "deviceName": "SM-T390",
    "marketingName": "Galaxy Tab Active 2",
    "manufacturer": "Samsung",
    "brand": "Samsung",
    "display": {
      "width": 1280,
      "height": 800,
      "touch": true,
      "size": null
    },
    "dualOrientation": true,
    "type": "fone-pad",
    "simCount": 1,
    "market": {
      "regions": [],
      "countries": [],
      "vendors": []
    },
    "connections": [],
    "platform": "android",
    "variants": []
  },
  "samsung sm-t395": {
    "deviceName": "SM-T395",
    "marketingName": "Galaxy Tab Active 2",
    "manufacturer": "Samsung",
    "brand": "Samsung",
    "display": {
      "width": 1280,
      "height": 800,
      "touch": true,
      "size": null
    },
    "dualOrientation": true,
    "type": "fone-pad",
    "simCount": 1,
    "market": {
      "regions": [],
      "countries": [],
      "vendors": []
    },
    "connections": [],
    "platform": "android",
    "variants": []
  },
  "samsung sm-t377v": {
    "deviceName": "SM-T377V",
    "marketingName": "Galaxy Tab E",
    "manufacturer": "Samsung",
    "brand": "Samsung",
    "display": {
      "width": 1280,
      "height": 800,
      "touch": true,
      "size": 8
    },
    "dualOrientation": true,
    "type": "fone-pad",
    "simCount": 1,
    "market": {
      "regions": [],
      "countries": [],
      "vendors": []
    },
    "connections": [
      "XLTE"
    ],
    "platform": "android",
    "variants": []
  },
  "samsung sm-t377w": {
    "deviceName": "SM-T377W",
    "marketingName": "Galaxy Tab E",
    "manufacturer": "Samsung",
    "brand": "Samsung",
    "display": {
      "width": 1280,
      "height": 800,
      "touch": true,
      "size": 8
    },
    "dualOrientation": true,
    "type": "fone-pad",
    "simCount": 1,
    "market": {
      "regions": [],
      "countries": [],
      "vendors": []
    },
    "connections": [
      "UMTS",
      "HSUPA",
      "HSDPA",
      "HSPA+",
      "LTE"
    ],
    "platform": "android",
    "variants": []
  },
  "samsung sm-t375s": {
    "deviceName": "SM-T375S",
    "marketingName": "Galaxy Tab E (8.0)",
    "manufacturer": "Samsung",
    "brand": "Samsung",
    "display": {
      "width": 1280,
      "height": 800,
      "touch": true,
      "size": null
    },
    "dualOrientation": true,
    "type": "fone-pad",
    "simCount": 1,
    "market": {
      "regions": [],
      "countries": [],
      "vendors": []
    },
    "connections": [
      "LTE"
    ],
    "platform": "android",
    "variants": []
  },
  "samsung sm-t561": {
    "deviceName": "SM-T561",
    "marketingName": "Galaxy Tab E 9.6 Bianco 3G",
    "manufacturer": "Samsung",
    "brand": "Samsung",
    "display": {
      "width": 1280,
      "height": 800,
      "touch": true,
      "size": null
    },
    "dualOrientation": true,
    "type": "fone-pad",
    "simCount": 1,
    "market": {
      "regions": [],
      "countries": [],
      "vendors": []
    },
    "connections": [
      "GSM"
    ],
    "platform": "android",
    "variants": []
  },
  "samsung sm-t525": {
    "deviceName": "SM-T525",
    "marketingName": "Galaxy Tab Pro 10.1",
    "manufacturer": "Samsung",
    "brand": "Samsung",
    "display": {
      "width": 2560,
      "height": 1600,
      "touch": true,
      "size": null
    },
    "dualOrientation": true,
    "type": "fone-pad",
    "simCount": 1,
    "market": {
      "regions": [],
      "countries": [],
      "vendors": []
    },
    "connections": [
      "LTE"
    ],
    "platform": "android",
    "variants": []
  },
  "samsung sm-t325": {
    "deviceName": "SM-T325",
    "marketingName": "Galaxy Tab Pro 8.4",
    "manufacturer": "Samsung",
    "brand": "Samsung",
    "display": {
      "width": 2560,
      "height": 1600,
      "touch": true,
      "size": null
    },
    "dualOrientation": true,
    "type": "fone-pad",
    "simCount": 1,
    "market": {
      "regions": [],
      "countries": [],
      "vendors": []
    },
    "connections": [
      "LTE"
    ],
    "platform": "android",
    "variants": []
  },
  "samsung sm-w708y": {
    "deviceName": "SM-W708Y",
    "marketingName": "Galaxy Tab Pro S (12.0)",
    "manufacturer": "Samsung",
    "brand": "Samsung",
    "display": {
      "width": 2160,
      "height": 1440,
      "touch": true,
      "size": null
    },
    "dualOrientation": true,
    "type": "fone-pad",
    "simCount": 1,
    "market": {
      "regions": [],
      "countries": [],
      "vendors": []
    },
    "connections": [
      "LTE"
    ],
    "platform": null,
    "variants": []
  },
  "samsung sm-t805": {
    "deviceName": "SM-T805",
    "marketingName": "Galaxy Tab S 10.5",
    "manufacturer": "Samsung",
    "brand": "Samsung",
    "display": {
      "width": 2560,
      "height": 1600,
      "touch": true,
      "size": null
    },
    "dualOrientation": true,
    "type": "fone-pad",
    "simCount": 1,
    "market": {
      "regions": [],
      "countries": [],
      "vendors": []
    },
    "connections": [
      "LTE"
    ],
    "platform": "android",
    "variants": []
  },
  "samsung sm-t807j": {
    "deviceName": "SM-T807J",
    "marketingName": "Galaxy Tab S 10.5",
    "manufacturer": "Samsung",
    "brand": "Samsung",
    "display": {
      "width": 2560,
      "height": 1600,
      "touch": true,
      "size": null
    },
    "dualOrientation": true,
    "type": "fone-pad",
    "simCount": 1,
    "market": {
      "regions": [],
      "countries": [],
      "vendors": []
    },
    "connections": [],
    "platform": "android",
    "variants": []
  },
  "samsung sm-t705": {
    "deviceName": "SM-T705",
    "marketingName": "Galaxy Tab S 8.4",
    "manufacturer": "Samsung",
    "brand": "Samsung",
    "display": {
      "width": 1280,
      "height": 800,
      "touch": true,
      "size": null
    },
    "dualOrientation": true,
    "type": "fone-pad",
    "simCount": 1,
    "market": {
      "regions": [],
      "countries": [],
      "vendors": []
    },
    "connections": [
      "LTE"
    ],
    "platform": "android",
    "variants": []
  },
  "samsung sm-t705m": {
    "deviceName": "SM-T705M",
    "marketingName": "Galaxy Tab S 8.4",
    "manufacturer": "Samsung",
    "brand": "Samsung",
    "display": {
      "width": 1280,
      "height": 800,
      "touch": true,
      "size": null
    },
    "dualOrientation": true,
    "type": "fone-pad",
    "simCount": 1,
    "market": {
      "regions": [],
      "countries": [],
      "vendors": []
    },
    "connections": [
      "LTE"
    ],
    "platform": "android",
    "variants": []
  },
  "samsung sm-t815": {
    "deviceName": "SM-T815",
    "marketingName": "Galaxy Tab S2 (9.7, 2015)",
    "manufacturer": "Samsung",
    "brand": "Samsung",
    "display": {
      "width": 2048,
      "height": 1536,
      "touch": true,
      "size": null
    },
    "dualOrientation": true,
    "type": "fone-pad",
    "simCount": 1,
    "market": {
      "regions": [],
      "countries": [],
      "vendors": []
    },
    "connections": [
      "LTE"
    ],
    "platform": "android",
    "variants": []
  },
  "samsung sm-t815y": {
    "deviceName": "SM-T815Y",
    "marketingName": "Galaxy Tab S2 (9.7, 2015)",
    "manufacturer": "Samsung",
    "brand": "Samsung",
    "display": {
      "width": 2048,
      "height": 1536,
      "touch": true,
      "size": null
    },
    "dualOrientation": true,
    "type": "fone-pad",
    "simCount": 1,
    "market": {
      "regions": [],
      "countries": [],
      "vendors": []
    },
    "connections": [
      "LTE"
    ],
    "platform": "android",
    "variants": []
  },
  "samsung sm-t819": {
    "deviceName": "SM-T819",
    "marketingName": "Galaxy Tab S2 (9.7, 2016)",
    "manufacturer": "Samsung",
    "brand": "Samsung",
    "display": {
      "width": 2048,
      "height": 1536,
      "touch": true,
      "size": null
    },
    "dualOrientation": true,
    "type": "fone-pad",
    "simCount": 1,
    "market": {
      "regions": [],
      "countries": [],
      "vendors": []
    },
    "connections": [
      "LTE"
    ],
    "platform": "android",
    "variants": []
  },
  "samsung sm-t715y": {
    "deviceName": "SM-T715Y",
    "marketingName": "Galaxy Tab S2 8.0",
    "manufacturer": "Samsung",
    "brand": "Samsung",
    "display": {
      "width": 2048,
      "height": 1536,
      "touch": true,
      "size": null
    },
    "dualOrientation": true,
    "type": "fone-pad",
    "simCount": 1,
    "market": {
      "regions": [],
      "countries": [],
      "vendors": []
    },
    "connections": [
      "LTE"
    ],
    "platform": "windows phone",
    "variants": []
  },
  "samsung sm-t715": {
    "deviceName": "SM-T715",
    "marketingName": "Galaxy Tab S2 8.0 (2015)",
    "manufacturer": "Samsung",
    "brand": "Samsung",
    "display": {
      "width": 2048,
      "height": 1536,
      "touch": true,
      "size": null
    },
    "dualOrientation": true,
    "type": "fone-pad",
    "simCount": 1,
    "market": {
      "regions": [],
      "countries": [],
      "vendors": []
    },
    "connections": [
      "LTE"
    ],
    "platform": "android",
    "variants": []
  },
  "samsung sm-t719": {
    "deviceName": "SM-T719",
    "marketingName": "Galaxy Tab S2 8.0 (2016)",
    "manufacturer": "Samsung",
    "brand": "Samsung",
    "display": {
      "width": 2048,
      "height": 1536,
      "touch": true,
      "size": null
    },
    "dualOrientation": true,
    "type": "fone-pad",
    "simCount": 1,
    "market": {
      "regions": [],
      "countries": [],
      "vendors": []
    },
    "connections": [
      "LTE"
    ],
    "platform": "android",
    "variants": []
  },
  "samsung sm-t719n": {
    "deviceName": "SM-T719N",
    "marketingName": "Galaxy Tab S2 8.0 (2016)",
    "manufacturer": "Samsung",
    "brand": "Samsung",
    "display": {
      "width": 2048,
      "height": 1536,
      "touch": true,
      "size": null
    },
    "dualOrientation": true,
    "type": "fone-pad",
    "simCount": 1,
    "market": {
      "regions": [],
      "countries": [],
      "vendors": []
    },
    "connections": [
      "LTE"
    ],
    "platform": "android",
    "variants": []
  },
  "samsung sm-t825": {
    "deviceName": "SM-T825",
    "marketingName": "Galaxy Tab S3 (9.7)",
    "manufacturer": "Samsung",
    "brand": "Samsung",
    "display": {
      "width": 2048,
      "height": 1536,
      "touch": true,
      "size": null
    },
    "dualOrientation": true,
    "type": "fone-pad",
    "simCount": 1,
    "market": {
      "regions": [],
      "countries": [],
      "vendors": []
    },
    "connections": [
      "LTE"
    ],
    "platform": "android",
    "variants": []
  },
  "samsung sm-t835": {
    "deviceName": "SM-T835",
    "marketingName": "Galaxy Tab S4 (10.5)",
    "manufacturer": "Samsung",
    "brand": "Samsung",
    "display": {
      "width": 2560,
      "height": 1600,
      "touch": true,
      "size": null
    },
    "dualOrientation": true,
    "type": "fone-pad",
    "simCount": 1,
    "market": {
      "regions": [],
      "countries": [],
      "vendors": []
    },
    "connections": [
      "LTE"
    ],
    "platform": "android",
    "variants": []
  },
  "samsung sm-t677v": {
    "deviceName": "SM-T677V",
    "marketingName": "Galaxy Tab View",
    "manufacturer": "Samsung",
    "brand": "Samsung",
    "display": {
      "width": 1920,
      "height": 1080,
      "touch": true,
      "size": null
    },
    "dualOrientation": true,
    "type": "fone-pad",
    "simCount": 1,
    "market": {
      "regions": [],
      "countries": [],
      "vendors": []
    },
    "connections": [
      "XLTE"
    ],
    "platform": "android",
    "variants": []
  }
}
