{
  "general siemens device": {
    "codename": "general Siemens Device",
    "marketingName": "general Siemens Device",
    "manufacturer": "Siemens",
    "brand": "Siemens",
    "platform": null,
    "type": "feature-phone",
    "pointingMethod": null,
    "resolutionWidth": null,
    "resolutionHeight": null,
    "dualOrientation": false
  },
  "benq-siemens cf61": {
    "codename": "CF61",
    "marketingName": "CF61",
    "manufacturer": "BenQ-Siemens",
    "brand": "BenQ-Siemens",
    "platform": "java",
    "type": "feature-phone",
    "pointingMethod": "stylus",
    "resolutionWidth": 128,
    "resolutionHeight": 160,
    "dualOrientation": false
  },
  "siemens s65": {
    "codename": "S65",
    "marketingName": "S65",
    "manufacturer": "Siemens",
    "brand": "Siemens",
    "platform": "java",
    "type": "feature-phone",
    "pointingMethod": "stylus",
    "resolutionWidth": 132,
    "resolutionHeight": 176,
    "dualOrientation": false
  },
  "siemens sl45": {
    "codename": "SL45",
    "marketingName": "SL45",
    "manufacturer": "Siemens",
    "brand": "Siemens",
    "platform": "java",
    "type": "feature-phone",
    "pointingMethod": "stylus",
    "resolutionWidth": 101,
    "resolutionHeight": 80,
    "dualOrientation": false
  },
  "siemens sl45i": {
    "codename": "SL45i",
    "marketingName": "SL45i",
    "manufacturer": "Siemens",
    "brand": "Siemens",
    "platform": "java",
    "type": "feature-phone",
    "pointingMethod": "stylus",
    "resolutionWidth": 101,
    "resolutionHeight": 80,
    "dualOrientation": false
  }
}
