{
  "general vestel device": {
    "deviceName": "general Vestel device",
    "marketingName": "general Vestel device",
    "manufacturer": "vestel",
    "brand": "vestel",
    "display": {
      "width": null,
      "height": null,
      "touch": true,
      "size": null
    },
    "type": "smartphone",
    "platform": "android"
  },
  "vestel 5000 2gb": {
    "deviceName": "5000 2GB",
    "marketingName": "5000 2GB",
    "manufacturer": "vestel",
    "brand": "vestel",
    "display": {
      "width": 1280,
      "height": 720,
      "touch": true,
      "size": 5
    },
    "type": "smartphone",
    "platform": "android"
  },
  "vestel venus v3 5020": {
    "deviceName": "Venus V3 5020",
    "marketingName": "Venus V3 5020",
    "manufacturer": "vestel",
    "brand": "vestel",
    "display": {
      "width": 1280,
      "height": 720,
      "touch": true,
      "size": 5
    },
    "type": "smartphone",
    "platform": "android"
  },
  "vestel venus v3 5570": {
    "deviceName": "Venus V3 5570",
    "marketingName": "Venus V3 5570",
    "manufacturer": "vestel",
    "brand": "vestel",
    "display": {
      "width": 1920,
      "height": 1080,
      "touch": true,
      "size": 5.5
    },
    "type": "smartphone",
    "platform": "android"
  },
  "vestel venus z10": {
    "deviceName": "Venus Z10",
    "marketingName": "Venus Z10",
    "manufacturer": "vestel",
    "brand": "vestel",
    "display": {
      "width": 1920,
      "height": 1080,
      "touch": true,
      "size": 5.2
    },
    "type": "smartphone",
    "platform": "android"
  }
}
