{
  "huawei y600-u151": {
    "codename": "Y600-U151",
    "marketingName": "Ascend Y600",
    "manufacturer": "Huawei",
    "brand": "Huawei",
    "platform": "android",
    "type": "smartphone",
    "pointingMethod": "touchscreen",
    "resolutionWidth": 480,
    "resolutionHeight": 854,
    "dualOrientation": true,
    "colors": null
  },
  "huawei h60-l04": {
    "codename": "H60-L04",
    "marketingName": "Honor 6 LTE, HSDPA",
    "manufacturer": "Huawei",
    "brand": "Huawei",
    "platform": "android",
    "type": "smartphone",
    "pointingMethod": "touchscreen",
    "resolutionWidth": 1080,
    "resolutionHeight": 1920,
    "dualOrientation": true,
    "colors": null
  },
  "huawei h60-l01": {
    "codename": "H60-L01",
    "marketingName": "Honor 6 LTE",
    "manufacturer": "Huawei",
    "brand": "Huawei",
    "platform": "android",
    "type": "smartphone",
    "pointingMethod": "touchscreen",
    "resolutionWidth": 1080,
    "resolutionHeight": 1920,
    "dualOrientation": true,
    "colors": null
  },
  "huawei h60-l02": {
    "codename": "H60-L02",
    "marketingName": "Honor 6 LTE, HSDPA",
    "manufacturer": "Huawei",
    "brand": "Huawei",
    "platform": "android",
    "type": "smartphone",
    "pointingMethod": "touchscreen",
    "resolutionWidth": 1080,
    "resolutionHeight": 1920,
    "dualOrientation": true,
    "colors": null
  },
  "huawei h60-l12": {
    "codename": "H60-L12",
    "marketingName": "Honor 6 LTE",
    "manufacturer": "Huawei",
    "brand": "Huawei",
    "platform": "android",
    "type": "smartphone",
    "pointingMethod": "touchscreen",
    "resolutionWidth": 1080,
    "resolutionHeight": 1920,
    "dualOrientation": true,
    "colors": null
  },
  "huawei p6": {
    "codename": "P6",
    "marketingName": "Ascend P6",
    "manufacturer": "Huawei",
    "brand": "Huawei",
    "platform": "android",
    "type": "smartphone",
    "pointingMethod": "touchscreen",
    "resolutionWidth": 720,
    "resolutionHeight": 1280,
    "dualOrientation": true,
    "colors": null
  },
  "huawei g630-u10": {
    "codename": "G630-U10",
    "marketingName": "Ascend G630",
    "manufacturer": "Huawei",
    "brand": "Huawei",
    "platform": "android",
    "type": "smartphone",
    "pointingMethod": "touchscreen",
    "resolutionWidth": 720,
    "resolutionHeight": 1280,
    "dualOrientation": true,
    "colors": null
  },
  "huawei g606-t00": {
    "codename": "G606-T00",
    "marketingName": "Ascend G606",
    "manufacturer": "Huawei",
    "brand": "Huawei",
    "platform": "android",
    "type": "smartphone",
    "pointingMethod": "touchscreen",
    "resolutionWidth": 540,
    "resolutionHeight": 960,
    "dualOrientation": true,
    "colors": null
  },
  "huawei mha-l29": {
    "codename": "MHA-L29",
    "marketingName": "Mate 9 Dual SIM",
    "manufacturer": "Huawei",
    "brand": "Huawei",
    "platform": "android",
    "type": "smartphone",
    "pointingMethod": "touchscreen",
    "resolutionWidth": 1080,
    "resolutionHeight": 1920,
    "dualOrientation": true,
    "colors": null
  },
  "huawei cam-l21": {
    "codename": "CAM-L21",
    "marketingName": "Y6II",
    "manufacturer": "Huawei",
    "brand": "Huawei",
    "platform": "android",
    "type": "smartphone",
    "pointingMethod": "touchscreen",
    "resolutionWidth": 720,
    "resolutionHeight": 1280,
    "dualOrientation": true,
    "colors": null
  },
  "huawei ale-cl00": {
    "codename": "ALE-CL00",
    "marketingName": "P8 Lite Dual SIM",
    "manufacturer": "Huawei",
    "brand": "Huawei",
    "platform": "android",
    "type": "smartphone",
    "pointingMethod": "touchscreen",
    "resolutionWidth": 720,
    "resolutionHeight": 1280,
    "dualOrientation": true,
    "colors": null
  }
}
