{
    "prestigio psp5453duo": {
        "codename": "PSP5453DUO",
        "marketingName": "Multiphone 5453 Duo",
        "manufacturer": "Prestigio",
        "brand": "Prestigio",
        "platform": "android",
        "type": "smartphone",
        "pointingMethod": "touchscreen",
        "resolutionWidth": 540,
        "resolutionHeight": 960,
        "dualOrientation": true,
        "colors": null
    },
    "prestigio psp5505duo": {
        "codename": "PSP5505DUO",
        "marketingName": "MultiPhone 5505 Duo",
        "manufacturer": "Prestigio",
        "brand": "Prestigio",
        "platform": "android",
        "type": "smartphone",
        "pointingMethod": "touchscreen",
        "resolutionWidth": 540,
        "resolutionHeight": 960,
        "dualOrientation": true,
        "colors": null
    },
    "prestigio psp5508duo": {
        "codename": "PSP5508DUO",
        "marketingName": "MultiPhone 5508 Duo",
        "manufacturer": "Prestigio",
        "brand": "Prestigio",
        "platform": "android",
        "type": "smartphone",
        "pointingMethod": "touchscreen",
        "resolutionWidth": 720,
        "resolutionHeight": 1280,
        "dualOrientation": true,
        "colors": null
    },
    "prestigio psp5517duo": {
        "codename": "PSP5517DUO",
        "marketingName": "MultiPhone 5517 Duo",
        "manufacturer": "Prestigio",
        "brand": "Prestigio",
        "platform": "android",
        "type": "smartphone",
        "pointingMethod": "touchscreen",
        "resolutionWidth": 540,
        "resolutionHeight": 960,
        "dualOrientation": true,
        "colors": null
    }
}